[{"user_id": "39834947", "id": "935296401969434626", "screen_name": "DrRandPaul", "text": "This bill isn\u2019t going to pass by itself. We need your support: http://randpac.com/its-time-for-tax-reform http://pbs.twimg.com/ext_tw_video_thumb/935296279525117953/pu/img/Uztz5rh2Jwc3b6OD.jpg https://video.twimg.com/ext_tw_video/935296279525117953/pu/vid/240x240/cUoCPQdb9T7BwE2T.mp4", "time": "2017-11-27T18:56:53-05:00", "link": "https://www.twitter.com/DrRandPaul/statuses/935296401969434626", "source": "Twitter Web Client"}, {"user_id": "803694179079458816", "id": "935248701601275905", "screen_name": "SenKamalaHarris", "text": "The Consumer Financial Protection Bureau is a watchdog agency with the core mission to defend American consumers from predatory and fraudulent practices that can financially ruin you and your family.", "time": "2017-11-27T15:47:21-05:00", "link": "https://www.twitter.com/SenKamalaHarris/statuses/935248701601275905", "source": "Twitter Web Client"}, {"user_id": "229966028", "id": "935128466147696640", "screen_name": "SenRubioPress", "text": "RT @marcorubio This week as we move to #TaxReform will be working to expand access to #ChildTaxCredit by making it fully refundable against payroll taxes.", "time": "2017-11-27T07:49:34-05:00", "link": "https://www.twitter.com/marcorubio/statuses/935128378193141765", "source": "Twitter for iPhone"}, {"user_id": "2461810448", "id": "935306419498340352", "screen_name": "TeamPelosi", "text": "Another reason why repeal of #NetNeutrality\u00a0is terrible policy that will negatively impact everyone and end the internet as we know it, as President @BarackObama underscored. https://twitter.com/rokhanna/status/935302470464692225 QT @RoKhanna The FCC has just made it even harder for low-income families to afford internet access. Huge mistake. We should demand broadband for all. https://blavity.com/the-fcc-votes-to-limit-internet-access-for-low-income-households", "time": "2017-11-27T19:36:42-05:00", "link": "https://www.twitter.com/TeamPelosi/statuses/935306419498340352", "source": "Twitter for iPhone"}, {"user_id": "803694179079458816", "id": "935249084318978051", "screen_name": "SenKamalaHarris", "text": "If we want to fight predatory behavior in the future, we need to maintain a strong @CFPB.", "time": "2017-11-27T15:48:52-05:00", "link": "https://www.twitter.com/SenKamalaHarris/statuses/935249084318978051", "source": "Twitter Web Client"}, {"user_id": "39834947", "id": "935200549028487168", "screen_name": "DrRandPaul", "text": "Here's why I plan to vote for the Senate tax bill (and my colleagues should step up) https://buff.ly/2BhYZKz", "time": "2017-11-27T12:36:00-05:00", "link": "https://www.twitter.com/DrRandPaul/statuses/935200549028487168", "source": "Buffer"}, {"user_id": "29442313", "id": "935278485555249152", "screen_name": "SenSanders", "text": "RT @NBCPolitics Bernie Sanders hits the trail again, this time to fight GOP tax bill http://nbcnews.to/2k2m3K3", "time": "2017-11-27T17:45:42-05:00", "link": "https://www.twitter.com/NBCPolitics/statuses/935260997534797825", "source": "TweetDeck"}, {"user_id": "39834947", "id": "935239705251188737", "screen_name": "DrRandPaul", "text": "This bill isn\u2019t going to pass by itself, and there are still roadblocks. It's time for tax reform. https://buff.ly/2AaQVy3", "time": "2017-11-27T15:11:36-05:00", "link": "https://www.twitter.com/DrRandPaul/statuses/935239705251188737", "source": "Buffer"}, {"user_id": "2167097881", "id": "935311300942589953", "screen_name": "SenBooker", "text": ".@CoryBooker Statement on Labor Department\u2019s Fiduciary Rule Delay: http://bit.ly/2n9ED45", "time": "2017-11-27T19:56:06-05:00", "link": "https://www.twitter.com/SenBooker/statuses/935311300942589953", "source": "Buffer"}, {"user_id": "30354991", "id": "935330406458626048", "screen_name": "KamalaHarris", "text": "Before Thanksgiving, I visited with students at Al-Quds University on a trip to Israel. Visiting with these students was one of the many highlights of my trip. \nhttp://english.pnn.ps/2017/11/23/u-s-senator-kamala-harris-visits-al-quds-university-hears-intimately-from-students-about-their-experience/", "time": "2017-11-27T21:12:01-05:00", "link": "https://www.twitter.com/KamalaHarris/statuses/935330406458626048", "source": "Sprout Social"}, {"user_id": "30354991", "id": "935239809878151169", "screen_name": "KamalaHarris", "text": "Sign on if you agree: the free and open internet is a cornerstone of our society and must be protected at all costs. http://kamala.to/NetNeutrality", "time": "2017-11-27T15:12:01-05:00", "link": "https://www.twitter.com/KamalaHarris/statuses/935239809878151169", "source": "Sprout Social"}, {"user_id": "2461810448", "id": "935273723220889601", "screen_name": "TeamPelosi", "text": "Ruthless, deficit-exploding #GOPTaxScam:\n\n\u274c Raises taxes on 82 MILLION middle class families\n\n\u274c Sabotages the health care of 13 MILLION Americans\n\n\u274c Steals $1.5 TRILLION from Medicare and Medicaid\n\n\u2705 Gives tax breaks to top 1% and corporations that ship American jobs overseas", "time": "2017-11-27T17:26:46-05:00", "link": "https://www.twitter.com/TeamPelosi/statuses/935273723220889601", "source": "Twitter Web Client"}, {"user_id": "23022687", "id": "935230507771678720", "screen_name": "tedcruz", "text": "#CyberMonday \ud83c\udf85\ud83c\udf81 special... $35 \u2014&gt; http://bit.ly/2i6WC9D http://pbs.twimg.com/media/DPqbJk-XkAAL2EW.jpg https://video.twimg.com/amplify_video/935229616620494848/vid/690x360/QVHKKtS7MpWhsiy8.mp4", "time": "2017-11-27T14:35:03-05:00", "link": "https://www.twitter.com/tedcruz/statuses/935230507771678720", "source": "Twitter Ads"}, {"user_id": "216881337", "id": "935173144544981001", "screen_name": "RandPaul", "text": "Here's why I plan to vote for the Senate tax bill (and my colleagues should step up) http://www.foxnews.com/opinion/2017/11/27/sen-rand-paul-heres-why-plan-to-vote-for-senate-tax-bill-and-my-colleagues-should-step-up.html", "time": "2017-11-27T10:47:06-05:00", "link": "https://www.twitter.com/RandPaul/statuses/935173144544981001", "source": "Buffer"}, {"user_id": "15745368", "id": "935128378193141765", "screen_name": "marcorubio", "text": "This week as we move to #TaxReform will be working to expand access to #ChildTaxCredit by making it fully refundable against payroll taxes.", "time": "2017-11-27T07:49:13-05:00", "link": "https://www.twitter.com/marcorubio/statuses/935128378193141765", "source": "Twitter for iPad"}, {"user_id": "229966028", "id": "935212506808807425", "screen_name": "SenRubioPress", "text": "Critical that we raise #NorthKorea\u2019s horrific human rights violations against its own people while we work to stop the Kim regime\u2019s growing nuclear and missile threats. http://nyti.ms/2AgiEeR", "time": "2017-11-27T13:23:31-05:00", "link": "https://www.twitter.com/SenRubioPress/statuses/935212506808807425", "source": "Twitter Web Client"}, {"user_id": "2167097881", "id": "935310924390588416", "screen_name": "SenBooker", "text": "Some states have already started warning families that their children may be kicked off health insurance because CHIP funding is running out\u2014Senate Republicans must act to extend funding immediately: http://slate.me/2Bi4eKx", "time": "2017-11-27T19:54:36-05:00", "link": "https://www.twitter.com/SenBooker/statuses/935310924390588416", "source": "Buffer"}, {"user_id": "803694179079458816", "id": "935265633780092929", "screen_name": "SenKamalaHarris", "text": "\u201cSessions is methodically reshaping the Justice Department to reflect his nationalist ideology and hardline views.\u201d\n\nWe can\u2019t sleep on this. https://www.washingtonpost.com/world/national-security/while-eyes-are-on-russia-sessions-dramatically-reshapes-the-justice-department/2017/11/24/dd52d66a-b8dd-11e7-9e58-e6288544af98_story.html?utm_term=.4009e3908b40", "time": "2017-11-27T16:54:38-05:00", "link": "https://www.twitter.com/SenKamalaHarris/statuses/935265633780092929", "source": "Twitter Web Client"}, {"user_id": "30354991", "id": "935363122109599746", "screen_name": "KamalaHarris", "text": "Public comment for the proposed @NatlParkService entrance fee increase closes on December 22. Submit a comment and say NO: http://kamala.to/NPS", "time": "2017-11-27T23:22:01-05:00", "link": "https://www.twitter.com/KamalaHarris/statuses/935363122109599746", "source": "Sprout Social"}, {"user_id": "2167097881", "id": "935217666381549568", "screen_name": "SenBooker", "text": "Someone who calls the @CFPB a \"joke\" can't be trusted to fight for the interests of American consumers against powerful banks. #DefendCFPB http://wapo.st/2AbUlRM", "time": "2017-11-27T13:44:01-05:00", "link": "https://www.twitter.com/SenBooker/statuses/935217666381549568", "source": "Twitter Web Client"}, {"user_id": "803694179079458816", "id": "935296179289632768", "screen_name": "SenKamalaHarris", "text": "Republicans have said their plan is a \u201ctax cut for everyone.\u201d It\u2019s not. https://www.washingtonpost.com/news/wonk/wp/2017/11/26/senate-gop-tax-bill-hurts-the-poor-more-than-originally-thought-cbo-finds/?utm_term=.cdce2143dde7", "time": "2017-11-27T18:56:00-05:00", "link": "https://www.twitter.com/SenKamalaHarris/statuses/935296179289632768", "source": "Sprout Social"}, {"user_id": "23022687", "id": "935161591699591168", "screen_name": "tedcruz", "text": "Tuesday, November 28. 8 pm CT.\n\nRSVP NOW --&gt; https://www.facebook.com/events/1550710418356540/ #TXSen #CruzCrew http://pbs.twimg.com/media/DPpcbP_WkAATa_v.jpg", "time": "2017-11-27T10:01:12-05:00", "link": "https://www.twitter.com/tedcruz/statuses/935161591699591168", "source": "TweetDeck"}, {"user_id": "803694179079458816", "id": "935249229341175808", "screen_name": "SenKamalaHarris", "text": "@CFPB Mick Mulvaney, the man Trump is sending in to lead the @CFPB, has called it a \u201cjoke.\u201d He\u2019s flat-out wrong. The American people deserve someone who will stand up and fight for consumers.", "time": "2017-11-27T15:49:27-05:00", "link": "https://www.twitter.com/SenKamalaHarris/statuses/935249229341175808", "source": "Twitter Web Client"}, {"user_id": "2461810448", "id": "935140781278580736", "screen_name": "TeamPelosi", "text": "RT @dccc The GOP wants you to believe that raising taxes on teachers in order to hand tax breaks to private jet owners is good for everyday Americans.\n\nRT if you're not falling for it. #GOPTaxScam http://pbs.twimg.com/media/DPlBzEuWsAAzPwL.jpg", "time": "2017-11-27T08:38:30-05:00", "link": "https://www.twitter.com/dccc/statuses/934850746230738946", "source": "Twitter for iPhone"}, {"user_id": "23022687", "id": "935335188128718848", "screen_name": "tedcruz", "text": "My friend Hal Lambert will be on the @HughHewitt radio show tomorrow at 7:45am CT. Hope you'll tune in to hear his interview! http://www.hughhewitt.com", "time": "2017-11-27T21:31:01-05:00", "link": "https://www.twitter.com/tedcruz/statuses/935335188128718848", "source": "TweetDeck"}, {"user_id": "2167097881", "id": "935163422789992448", "screen_name": "SenBooker", "text": "RT @MarshallProj We teamed up with @teenvogue and @corybooker to listen to what reentry is really like. https://www.themarshallproject.org/2017/10/10/what-is-prison-like-for-women-and-girls?utm_medium=social&utm_campaign=sprout&utm_source=twitter", "time": "2017-11-27T10:08:29-05:00", "link": "https://www.twitter.com/MarshallProj/statuses/934829858135445505", "source": "TweetDeck"}, {"user_id": "30354991", "id": "935297210597691397", "screen_name": "KamalaHarris", "text": "Revoking #NetNeutrality would further the digital divide across the nation, for everyone from low-income families, to small business owners, to students.", "time": "2017-11-27T19:00:06-05:00", "link": "https://www.twitter.com/KamalaHarris/statuses/935297210597691397", "source": "Sprout Social"}, {"user_id": "30354991", "id": "935269506213179393", "screen_name": "KamalaHarris", "text": "The average American earning less than $30,000/year would be worse off by 2019 if the Senate GOP tax bill passes. And my Republican colleagues want to vote on this bill as early as this week. Keep calling. \nhttps://twitter.com/washingtonpost/status/935115227783487489 QT @washingtonpost Senate GOP tax bill hurts the poor more than originally thought, CBO finds http://wapo.st/2BfFwKD", "time": "2017-11-27T17:10:01-05:00", "link": "https://www.twitter.com/KamalaHarris/statuses/935269506213179393", "source": "Sprout Social"}, {"user_id": "23022687", "id": "935353350996004864", "screen_name": "tedcruz", "text": "RT @AndrewCMcCarthy Trump is right in #CFPB tiff - my @NRO column: http://www.nationalreview.com/article/454073/trump-vs-richard-cordray-president-right-cfpb", "time": "2017-11-27T22:43:11-05:00", "link": "https://www.twitter.com/AndrewCMcCarthy/statuses/935228073221545985", "source": "Twitter for iPhone"}, {"user_id": "15745368", "id": "935263851267928067", "screen_name": "marcorubio", "text": "There was a time in America when workers were heroes. #TaxReform must help not only companies but also millions of hard-working people who have not seen their wages rise. We can and must do both. http://pbs.twimg.com/ext_tw_video_thumb/935262726733074433/pu/img/TjN99SwS7wmLqLUn.jpg https://video.twimg.com/ext_tw_video/935262726733074433/pu/vid/320x180/2ygWaV8Vh4ip42QB.mp4", "time": "2017-11-27T16:47:33-05:00", "link": "https://www.twitter.com/marcorubio/statuses/935263851267928067", "source": "Twitter Web Client"}, {"user_id": "970207298", "id": "935205003295371264", "screen_name": "SenWarren", "text": "RT @MarkWarner Since Day 1, the main criticism of the @CFPB is that it\u2019s *too effective* at standing up for consumers. That speaks volumes. https://twitter.com/realDonaldTrump/status/934539256940417024 QT @realDonaldTrump The Consumer Financial Protection Bureau, or CFPB, has been a total disaster as run by the previous Administrations pick. Financial Institutions have been devastated and unable to properly serve the public. We will bring it back to life!", "time": "2017-11-27T12:53:42-05:00", "link": "https://www.twitter.com/MarkWarner/statuses/935203769473798146", "source": "Twitter for iPhone"}, {"user_id": "1074480192", "id": "935217092772679682", "screen_name": "SenTedCruz", "text": "Obama-era regulations on the internet stifle consumer freedom and must be repealed. I support @AjitPaiFCC\u2019s plan to restore internet freedom. http://bit.ly/2znVYvV", "time": "2017-11-27T13:41:45-05:00", "link": "https://www.twitter.com/SenTedCruz/statuses/935217092772679682", "source": "Twitter Web Client"}, {"user_id": "803694179079458816", "id": "935280073447542785", "screen_name": "SenKamalaHarris", "text": "By 2019, Americans earning less than $30,000 a year will be worse off under the Senate GOP tax bill\u2026 but corporations will still have big, permanent tax cuts.", "time": "2017-11-27T17:52:00-05:00", "link": "https://www.twitter.com/SenKamalaHarris/statuses/935280073447542785", "source": "Sprout Social"}, {"user_id": "15745368", "id": "935123489064878081", "screen_name": "marcorubio", "text": "As face mirrors face in water, so the heart reflects the person. Proverbs 27:19", "time": "2017-11-27T07:29:48-05:00", "link": "https://www.twitter.com/marcorubio/statuses/935123489064878081", "source": "Twitter for iPad"}, {"user_id": "216881337", "id": "935248886867873793", "screen_name": "RandPaul", "text": "RT @GOP You deserve to bring home more of your hard-earned money. That\u2019s why @RandPaul and the Senate Republicans are ready to deliver tax relief.\nhttp://www.foxnews.com/opinion/2017/11/27/sen-rand-paul-heres-why-plan-to-vote-for-senate-tax-bill-and-my-colleagues-should-step-up.html", "time": "2017-11-27T15:48:05-05:00", "link": "https://www.twitter.com/GOP/statuses/935229493467385856", "source": "Twitter Web Client"}, {"user_id": "15745368", "id": "935301897485012992", "screen_name": "marcorubio", "text": "This has to be the best uniforms ever worn on a football field.We should pass a law making them wear them for every game! https://twitter.com/navyathletics/status/935221867241197568 QT @NavyAthletics \ud83d\udea8 #ArmyNavy Uniform Release! \ud83d\udea8\n#NavyFootball will be wearing Under Armour Blue Angels Uniforms for the Army-Navy Game! @uafootball http://pbs.twimg.com/media/DPqTCvaXcAY5cta.jpg http://pbs.twimg.com/media/DPqTEpoXcAEcyYT.jpg http://pbs.twimg.com/media/DPqTErBX4AEAd4t.jpg http://pbs.twimg.com/media/DPqTEq-WsAI8DwC.jpg", "time": "2017-11-27T19:18:44-05:00", "link": "https://www.twitter.com/marcorubio/statuses/935301897485012992", "source": "Twitter for iPad"}, {"user_id": "29442313", "id": "935301836923396096", "screen_name": "SenSanders", "text": ".@SpeakerRyan and @SenateMajLdr, how much will you cut Medicare, Medicaid and Social Security to pay for a $1.4 trillion deficit increase? How much will you cut Pell Grants, WIC and Head Start? The people have a right to know. http://pbs.twimg.com/media/DPrb-nsW0AEoHvy.jpg http://pbs.twimg.com/media/DPrb_QpWAAEj52a.jpg", "time": "2017-11-27T19:18:29-05:00", "link": "https://www.twitter.com/SenSanders/statuses/935301836923396096", "source": "Twitter Web Client"}, {"user_id": "2461810448", "id": "935141283928080386", "screen_name": "TeamPelosi", "text": "The #GOPTaxScam \u2018hurts the poor more than originally thought, CBO finds\u2019\n\nhttps://www.washingtonpost.com/news/wonk/wp/2017/11/26/senate-gop-tax-bill-hurts-the-poor-more-than-originally-thought-cbo-finds/?tid=sm_tw&utm_term=.d50c3278dbe8", "time": "2017-11-27T08:40:30-05:00", "link": "https://www.twitter.com/TeamPelosi/statuses/935141283928080386", "source": "Twitter for iPhone"}, {"user_id": "803694179079458816", "id": "935248922309742592", "screen_name": "SenKamalaHarris", "text": "When I was CA\u2019s Attorney General, we had to fight tooth and nail to get relief for struggling families who were put in impossible financial positions by the foreclosure crisis, predatory for-profit colleges, payday lenders, the list goes on.", "time": "2017-11-27T15:48:13-05:00", "link": "https://www.twitter.com/SenKamalaHarris/statuses/935248922309742592", "source": "Twitter Web Client"}, {"user_id": "30354991", "id": "935186312604332032", "screen_name": "KamalaHarris", "text": "As former Attorney General of California, I know how critical the CFPB is to protecting consumers. What Trump is doing is flat out wrong. We must protect the CFPB. \nhttps://www.bloomberg.com/news/articles/2017-11-27/next-act-in-cfpb-drama-comes-when-dueling-bosses-show-up-to-lead", "time": "2017-11-27T11:39:26-05:00", "link": "https://www.twitter.com/KamalaHarris/statuses/935186312604332032", "source": "Sprout Social"}, {"user_id": "30354991", "id": "935204577347063810", "screen_name": "KamalaHarris", "text": "Reminder as we start this week: Republicans are still pushing a tax plan that would leave 13 million more Americans uninsured and raise premiums. Call Congress, then add this number to your speed dial \u2192 (202) 224-3121.", "time": "2017-11-27T12:52:01-05:00", "link": "https://www.twitter.com/KamalaHarris/statuses/935204577347063810", "source": "Sprout Social"}, {"user_id": "23022687", "id": "935292220332273664", "screen_name": "tedcruz", "text": "RT @TexasCruzer Great time at #EnchantChristmas with the #TexasCruzer!  #WeCruzN http://pbs.twimg.com/media/DPhQ1hwUQAAaJWh.jpg http://pbs.twimg.com/media/DPhQ1iKVoAA96Ck.jpg http://pbs.twimg.com/media/DPhQ1iJV4AYniq_.jpg http://pbs.twimg.com/media/DPhQ1iJUQAA6mId.jpg", "time": "2017-11-27T18:40:16-05:00", "link": "https://www.twitter.com/TexasCruzer/statuses/934585819536510976", "source": "TweetDeck"}]