[{"user_id": "15808765", "id": "1053018996075839489", "screen_name": "CoryBooker", "text": "RT @TIDEVINE Honored to Senator @CoryBooker in Colunbia today.   It was such a joy talking to him about his roots in municipal governments and when I told him what a big fan my mini me was of his and we had to get a selfie.  #ADevineLife #momlife #worklifeintegration #workingmom #councilwoman http://pbs.twimg.com/media/Dp0N2UXXcAAPLGB.jpg http://pbs.twimg.com/media/Dp0N3P4W4AEgEWF.jpg", "time": "2018-10-18T16:24:27-04:00", "link": "https://www.twitter.com/TIDEVINE/statuses/1053013145919348736", "source": "Twitter for iPhone"}, {"user_id": "23022687", "id": "1053078946324058117", "screen_name": "tedcruz", "text": "@Frazier7324 Great to visit with y'all! Thank you for your service to your community, our state, and this nation!", "time": "2018-10-18T20:22:40-04:00", "link": "https://www.twitter.com/tedcruz/statuses/1053078946324058117", "source": "Twitter Web Client"}, {"user_id": "1074480192", "id": "1053010791790768128", "screen_name": "SenTedCruz", "text": "RT @SenTedCruz Yesterday Burnet County Judge Oakley &amp; Llano County Judge Cunningham briefed me, @RepRWilliams, @DrBuckinghamTX, and state Rep. Terry Wilson on flood recovery efforts while we surveyed communities in Central Texas recently affected by flooding. --&gt; https://www.cruz.senate.gov/?p=press_release&id=4146 http://pbs.twimg.com/ext_tw_video_thumb/1052976739549294593/pu/img/KGYlXCsXDW9cCJlf.jpg https://video.twimg.com/ext_tw_video/1052976739549294593/pu/vid/320x180/yfFKplyFBWn1z9gQ.mp4?tag=5", "time": "2018-10-18T15:51:51-04:00", "link": "https://www.twitter.com/SenTedCruz/statuses/1052976801046253568", "source": "Twitter Lite"}, {"user_id": "15745368", "id": "1052937496026333184", "screen_name": "marcorubio", "text": "Disaster Unemployment Assistance is available to #Florida businesses &amp; residents whose employment or self-employment was lost or interrupted as a result of Hurricane.  To file a claim, go to http://www.FloridaJobs.org or call 1-800-385-3920 #sayfie", "time": "2018-10-18T11:00:36-04:00", "link": "https://www.twitter.com/marcorubio/statuses/1052937496026333184", "source": "Twitter for iPad"}, {"user_id": "23022687", "id": "1053069048651636736", "screen_name": "tedcruz", "text": "RT @J_Wade_Miller I choose @tedcruz for #TXSen because @betoorourke's \"Medicare-for-All\" plan would bankrupt Medicare for those who need it! #TXSen #TexasTownHall #ChooseCruz #KeepTexasRed", "time": "2018-10-18T19:43:20-04:00", "link": "https://www.twitter.com/J_Wade_Miller/statuses/1053058387360002048", "source": "Twitter Web Client"}, {"user_id": "216776631", "id": "1053012276180131840", "screen_name": "BernieSanders", "text": "After 2 years of cancer treatment  42% of patients over 50 in America depleted all of their assets.\n\nThis is the richest country in the history of the world. People should not have to choose between bankruptcy and their health. #MedicareForAll", "time": "2018-10-18T15:57:45-04:00", "link": "https://www.twitter.com/BernieSanders/statuses/1053012276180131840", "source": "TweetDeck"}, {"user_id": "29442313", "id": "1052940360421400576", "screen_name": "SenSanders", "text": "I have long been troubled by the nature of the relationship between the U.S. and Saudi Arabia. It's time for us to thoroughly reevaluate that relationship. http://pbs.twimg.com/amplify_video_thumb/1052936839169040384/img/QThgWUSjDC76TWa6.jpg https://video.twimg.com/amplify_video/1052936839169040384/vid/240x240/7zOUk-wNcCOwhnvs.mp4?tag=8", "time": "2018-10-18T11:11:59-04:00", "link": "https://www.twitter.com/SenSanders/statuses/1052940360421400576", "source": "Media Studio"}, {"user_id": "29442313", "id": "1052930962500280321", "screen_name": "SenSanders", "text": "Shameful.\nhttps://www.vanityfair.com/news/2018/10/mitch-mcconnell-blames-the-poor-for-trumps-trillion-dollar-deficit", "time": "2018-10-18T10:34:38-04:00", "link": "https://www.twitter.com/SenSanders/statuses/1052930962500280321", "source": "Twitter Web Client"}, {"user_id": "15808765", "id": "1053006923388338176", "screen_name": "CoryBooker", "text": "RT @scdp .@CoryBooker: \u201cThe power of the people is greater than the people in power.\u201d \ud83d\ude4c http://pbs.twimg.com/media/Dpz2RciVAAAnqZf.jpg", "time": "2018-10-18T15:36:29-04:00", "link": "https://www.twitter.com/scdp/statuses/1052987201594806272", "source": "Twitter for iPhone"}, {"user_id": "15745368", "id": "1052937493421670402", "screen_name": "marcorubio", "text": ".@FLGovScott will be visiting @TeamTyndall today. It WILL be rebuilt stronger than ever. Most housing extensively damaged &amp; 10% a total loss. Here is drone video of housing area : https://www.dvidshub.net/video/632670/tyndall-air-force-base-view-housing-following-hurricane-michael #Sayfie", "time": "2018-10-18T11:00:35-04:00", "link": "https://www.twitter.com/marcorubio/statuses/1052937493421670402", "source": "Twitter for iPad"}, {"user_id": "1074480192", "id": "1052906190076829696", "screen_name": "SenTedCruz", "text": "The recent flooding in Central Texas has left many Texans displaced from their homes. Yesterday I visited with fellow Texans in Llano &amp; Burnet County to survey flood damage and to support them in their time of need. #TexansHelpingTexans http://pbs.twimg.com/media/DpysmBRWkAEqvQZ.jpg http://pbs.twimg.com/media/DpysmBSWwAIm6lR.jpg http://pbs.twimg.com/media/DpysmBRW4AAiE1z.jpg http://pbs.twimg.com/media/DpysmBUWkAE5l6w.jpg", "time": "2018-10-18T08:56:12-04:00", "link": "https://www.twitter.com/SenTedCruz/statuses/1052906190076829696", "source": "Twitter for iPhone"}, {"user_id": "970207298", "id": "1052998040217427969", "screen_name": "SenWarren", "text": "Corruption eats away at the heart of democracy. My bill to #EndCorruptionNow will make sure government represents the people \u2013 not just the wealthy and well-connected. https://www.usatoday.com/story/news/politics/2018/08/21/elizabeth-warren-wants-lifetime-ban-politicians-becoming-lobbyists/1058677002/", "time": "2018-10-18T15:01:11-04:00", "link": "https://www.twitter.com/SenWarren/statuses/1052998040217427969", "source": "Twitter Web Client"}, {"user_id": "15745368", "id": "1052937488589889536", "screen_name": "marcorubio", "text": ".@USDA has approved @FLGovScott request to waive timely reporting of food loss to households participating in the SNAP program. That now allows households in these affected counties to make a request for replacement of SNAP benefits through October 30, 2018. #Sayfie", "time": "2018-10-18T11:00:34-04:00", "link": "https://www.twitter.com/marcorubio/statuses/1052937488589889536", "source": "Twitter for iPad"}, {"user_id": "216776631", "id": "1052932262151491584", "screen_name": "BernieSanders", "text": "RT @LizForIndiana Friday at 11 am in Dunn Meadow in BLOOMINGTON! http://pbs.twimg.com/media/Dpwf5bTXgAAbs-I.jpg", "time": "2018-10-18T10:39:48-04:00", "link": "https://www.twitter.com/LizForIndiana/statuses/1052751488802525184", "source": "Twitter Web Client"}, {"user_id": "1074480192", "id": "1052976801046253568", "screen_name": "SenTedCruz", "text": "Yesterday Burnet County Judge Oakley &amp; Llano County Judge Cunningham briefed me, @RepRWilliams, @DrBuckinghamTX, and state Rep. Terry Wilson on flood recovery efforts while we surveyed communities in Central Texas recently affected by flooding. --&gt; https://www.cruz.senate.gov/?p=press_release&id=4146 http://pbs.twimg.com/ext_tw_video_thumb/1052976739549294593/pu/img/KGYlXCsXDW9cCJlf.jpg https://video.twimg.com/ext_tw_video/1052976739549294593/pu/vid/320x180/yfFKplyFBWn1z9gQ.mp4?tag=5", "time": "2018-10-18T13:36:47-04:00", "link": "https://www.twitter.com/SenTedCruz/statuses/1052976801046253568", "source": "Twitter Lite"}, {"user_id": "23022687", "id": "1053061916363513856", "screen_name": "tedcruz", "text": "Texas is booming. \n\nLet's keep it that way. \n\nLet's #KeepTexasRed! #TXSen", "time": "2018-10-18T19:15:00-04:00", "link": "https://www.twitter.com/tedcruz/statuses/1053061916363513856", "source": "Twitter Ads Composer"}, {"user_id": "2167097881", "id": "1053030967118565381", "screen_name": "SenBooker", "text": "Congratulations to Hoboken, Jersey City, and Woodbury, NJ for earning perfect scores in this year\u2019s Municipal Equality Index report from the Human Rights Campaign -&gt; https://outinjersey.net/three-nj-municipalities-receive-highest-score-for-lgbt-policy-and-services/", "time": "2018-10-18T17:12:01-04:00", "link": "https://www.twitter.com/SenBooker/statuses/1053030967118565381", "source": "Buffer"}, {"user_id": "216776631", "id": "1053035492197814272", "screen_name": "BernieSanders", "text": "Donald Trump and Mitch McConnell want to cut Medicare and Social Security.\n\nWe want to expand them.", "time": "2018-10-18T17:30:00-04:00", "link": "https://www.twitter.com/BernieSanders/statuses/1053035492197814272", "source": "TweetDeck"}, {"user_id": "2167097881", "id": "1053006227305836545", "screen_name": "SenBooker", "text": "RT @SenDuckworth Glad my bipartisan bill w @senrobportman, @SenBrianSchatz, &amp; @SenBooker to help reform the criminal justice system, reduce recidivism and save taxpayer dollars is gaining support from several #CivilRights orgs and criminal justice leaders. Read more here: https://www.duckworth.senate.gov/news/press-releases/bipartisan-duckworth-portman-schatz-booker-bill-to-help-reduce-recidivism-rates-gains-support-from-criminal-justice-leaders-and-civil-rights-organizations", "time": "2018-10-18T15:33:43-04:00", "link": "https://www.twitter.com/SenDuckworth/statuses/1053006034095226880", "source": "TweetDeck"}, {"user_id": "23022687", "id": "1052998744210329600", "screen_name": "tedcruz", "text": "RT @FoxFriendsFirst Protesters harass Senator Ted Cruz over his vote to confirm Justice Kavanaugh http://pbs.twimg.com/media/DpyWGaUWkAEFxpR.jpg", "time": "2018-10-18T15:03:59-04:00", "link": "https://www.twitter.com/FoxFriendsFirst/statuses/1052997743835136000", "source": "Twitter for iPhone"}, {"user_id": "15745368", "id": "1052872587594817537", "screen_name": "marcorubio", "text": "The LORD supports all who are falling and raises up all who are bowed down. Psalms 145:14", "time": "2018-10-18T06:42:40-04:00", "link": "https://www.twitter.com/marcorubio/statuses/1052872587594817537", "source": "Twitter for iPad"}, {"user_id": "23022687", "id": "1053029383340998657", "screen_name": "tedcruz", "text": "Texas is booming and seeing the benefits of low taxes &amp; low regs:\n\nLowest unemployment in 49 yrs\n\nLowest Black unemployment ever\n\nLowest Hispanic unemployment ever\n\nLowest Youth unemployment in 52 yrs\n\nLet's keep it that way. \n\nLet's #KeepTexasRed: https://www.tedcruz.org/keeptexasred/ #TXSen", "time": "2018-10-18T17:05:43-04:00", "link": "https://www.twitter.com/tedcruz/statuses/1053029383340998657", "source": "Twitter Ads Composer"}, {"user_id": "803694179079458816", "id": "1052960660798214144", "screen_name": "SenKamalaHarris", "text": "It is absolutely unconscionable that while many families continue to struggle, President Trump and Republicans in Congress are giving tax cuts to the top 1% and corporations while threatening Social Security and Medicare. It\u2019s time to change that.", "time": "2018-10-18T12:32:39-04:00", "link": "https://www.twitter.com/SenKamalaHarris/statuses/1052960660798214144", "source": "Twitter Web Client"}, {"user_id": "970207298", "id": "1053058295752208384", "screen_name": "SenWarren", "text": "The Saudi regime's brutal murder of journalist Jamal Khashoggi shows us that some will stop at nothing to silence the truth. His final column, published today, is a piercing example of the importance of a free press. I hope @realDonaldTrump reads it. https://www.washingtonpost.com/opinions/global-opinions/jamal-khashoggi-what-the-arab-world-needs-most-is-free-expression/2018/10/17/adfc8c44-d21d-11e8-8c22-fa2ef74bd6d6_story.html?utm_term=.31a0fcd2e82c", "time": "2018-10-18T19:00:37-04:00", "link": "https://www.twitter.com/SenWarren/statuses/1053058295752208384", "source": "Twitter Web Client"}, {"user_id": "15745368", "id": "1052944603790368769", "screen_name": "marcorubio", "text": "Must not accept a strategic alliance with #SaudiArabia which requires our silence when they butcher a political critic.\n\nWe must:\n\n1. Hold everyone responsible for #KashoggiMurder accountable; &amp;\n\n2. Be clear on what is expected moving forward if they want to preserve our alliance", "time": "2018-10-18T11:28:50-04:00", "link": "https://www.twitter.com/marcorubio/statuses/1052944603790368769", "source": "Twitter for iPad"}, {"user_id": "15808765", "id": "1053095770667257856", "screen_name": "CoryBooker", "text": "RT @ebenezer_atl We\u2019re looking forward to it!! https://twitter.com/corybooker/status/1052969094469828608 QT @CoryBooker Excited and humbled to be the speaker for services at @ebenezer_atl, the pastoral home of Martin Luther King, Jr. in Atlanta this Sunday at 9am\u2014please join us if you're in the area!", "time": "2018-10-18T21:29:31-04:00", "link": "https://www.twitter.com/ebenezer_atl/statuses/1053026790313263104", "source": "Twitter for iPhone"}, {"user_id": "1379584350", "id": "1053062339543601153", "screen_name": "TeamTedCruz", "text": "Congressman O\u2019Rourke voted NO on a resolution supporting the officers and personnel who carry out the important mission of the United States Immigration and Customs Enforcement:\n\n\u2014&gt; http://clerk.house.gov/evs/2018/roll337.xml \n\n\u2014&gt; https://www.congress.gov/bill/115th-congress/house-resolution/990 #TexasTownHall #TXSen", "time": "2018-10-18T19:16:41-04:00", "link": "https://www.twitter.com/TeamTedCruz/statuses/1053062339543601153", "source": "Twitter for iPhone"}, {"user_id": "15808765", "id": "1053007005659648000", "screen_name": "CoryBooker", "text": "RT @scdp \u201cDemocracy is NOT a spectator sport. Right now we are called to stand up and participate to make sure we have a democracy to pass on to our children.\u201d \u2014 @CoryBooker", "time": "2018-10-18T15:36:48-04:00", "link": "https://www.twitter.com/scdp/statuses/1052989886607880194", "source": "Twitter for iPhone"}, {"user_id": "229966028", "id": "1052938213692755969", "screen_name": "SenRubioPress", "text": "Today marks 72 days since the #Maduro regime arbitrarily detained opposition leader @JuanRequesens. The regime must free all political prisoners, Maduro and his cronies are responsible for the welfare of ALL prisoners. http://pbs.twimg.com/media/DpzJp8WXgAIWN0k.jpg", "time": "2018-10-18T11:03:27-04:00", "link": "https://www.twitter.com/SenRubioPress/statuses/1052938213692755969", "source": "Twitter Web Client"}, {"user_id": "30354991", "id": "1053121055743717376", "screen_name": "KamalaHarris", "text": "Affordable Care Act open enrollment is right now in California. Save yourself the stress over the holiday season and sign up today at http://coveredca.com. \nhttps://twitter.com/sfchronicle/status/1051842017578377217 QT @sfchronicle Covered California health insurance signups begin for those without benefits. \nhttps://www.sfchronicle.com/business/article/Covered-California-health-insurance-signups-begin-13305395.php http://pbs.twimg.com/media/DpjkvXEXcAAsDi1.jpg", "time": "2018-10-18T23:10:00-04:00", "link": "https://www.twitter.com/KamalaHarris/statuses/1053121055743717376", "source": "Sprout Social"}, {"user_id": "23022687", "id": "1052954366087434240", "screen_name": "tedcruz", "text": "RT @SenTedCruz The recent flooding in Central Texas has left many Texans displaced from their homes. Yesterday I visited with fellow Texans in Llano &amp; Burnet County to survey flood damage and to support them in their time of need. #TexansHelpingTexans http://pbs.twimg.com/media/DpysmBRWkAEqvQZ.jpg http://pbs.twimg.com/media/DpysmBSWwAIm6lR.jpg http://pbs.twimg.com/media/DpysmBRW4AAiE1z.jpg http://pbs.twimg.com/media/DpysmBUWkAE5l6w.jpg", "time": "2018-10-18T12:07:38-04:00", "link": "https://www.twitter.com/SenTedCruz/statuses/1052906190076829696", "source": "Twitter Web Client"}, {"user_id": "15808765", "id": "1053006835849019392", "screen_name": "CoryBooker", "text": "RT @scdp Let\u2019s not accept things the way they are. Let\u2019s take responsibility for changing them. We can do that THIS NOVEMBER 6th! @CoryBooker http://pbs.twimg.com/ext_tw_video_thumb/1052989368846209025/pu/img/5UDUbaOZjZnoq0YW.jpg https://video.twimg.com/ext_tw_video/1052989368846209025/pu/vid/240x240/GOERHolP5Rp3giM8.mp4?tag=5", "time": "2018-10-18T15:36:08-04:00", "link": "https://www.twitter.com/scdp/statuses/1052989880471556096", "source": "Twitter for iPhone"}, {"user_id": "23022687", "id": "1053059802862178304", "screen_name": "tedcruz", "text": "Cruz announces bill to end separation of immigrant families | #TexasTownHall  https://thehill.com/homenews/senate/392892-cruz-announces-bill-to-end-separation-of-immigrant-families", "time": "2018-10-18T19:06:36-04:00", "link": "https://www.twitter.com/tedcruz/statuses/1053059802862178304", "source": "Twitter for iPhone"}, {"user_id": "23022687", "id": "1053052052140670978", "screen_name": "tedcruz", "text": "A clear choice for Texas... #ChooseCruz! #TXSen", "time": "2018-10-18T18:35:48-04:00", "link": "https://www.twitter.com/tedcruz/statuses/1053052052140670978", "source": "Twitter Ads Composer"}, {"user_id": "803694179079458816", "id": "1052960856856772608", "screen_name": "SenKamalaHarris", "text": "The LIFT the Middle Class Act would positively impact an estimated one in every two workers and one in every three children in America. The rich and powerful are doing just fine. We need to do something for the middle class.", "time": "2018-10-18T12:33:25-04:00", "link": "https://www.twitter.com/SenKamalaHarris/statuses/1052960856856772608", "source": "Twitter Web Client"}, {"user_id": "23022687", "id": "1053065690842783744", "screen_name": "tedcruz", "text": "ICYMI: My closing statement from the #TexasDebate on Tuesday. #ChooseCruz #TXSen", "time": "2018-10-18T19:30:00-04:00", "link": "https://www.twitter.com/tedcruz/statuses/1053065690842783744", "source": "Twitter Ads Composer"}, {"user_id": "29442313", "id": "1053068885690404864", "screen_name": "SenSanders", "text": "We cannot have an ally who murders a dissident in cold blood, in their own consulate. That is unacceptable by any government, but especially by one so closely aligned with the United States.", "time": "2018-10-18T19:42:42-04:00", "link": "https://www.twitter.com/SenSanders/statuses/1053068885690404864", "source": "TweetDeck"}, {"user_id": "23022687", "id": "1053091714595020800", "screen_name": "tedcruz", "text": "I'm LIVE with @MarkDavis on Facebook... join the conversation: https://www.facebook.com/tedcruzpage/videos/734661320231996/ #TXSen http://pbs.twimg.com/media/Dp1VFC3WoAARalW.jpg", "time": "2018-10-18T21:13:24-04:00", "link": "https://www.twitter.com/tedcruz/statuses/1053091714595020800", "source": "Twitter Web Client"}, {"user_id": "15808765", "id": "1052969172316168200", "screen_name": "CoryBooker", "text": "My friend @Zack_Hawkins is running for NC House District 31 In Durham. I met Zack when he was President of the NC Young Democrats in 2008\u2014he was a leader then &amp; he\u2019s going to be an incredible leader for North Carolina. Early voting in NC just started &amp; ends Nov 3\u2014so please vote!", "time": "2018-10-18T13:06:28-04:00", "link": "https://www.twitter.com/CoryBooker/statuses/1052969172316168200", "source": "Buffer"}, {"user_id": "803694179079458816", "id": "1052960456132972544", "screen_name": "SenKamalaHarris", "text": "Everywhere I go, people tell me that one unexpected expense could throw their family into financial turmoil. Americans are working harder than ever, but wages are staying flat. Let\u2019s put some money back in their pockets.", "time": "2018-10-18T12:31:50-04:00", "link": "https://www.twitter.com/SenKamalaHarris/statuses/1052960456132972544", "source": "Twitter Web Client"}, {"user_id": "803694179079458816", "id": "1052960124900397056", "screen_name": "SenKamalaHarris", "text": "Today I announced the LIFT the Middle Class Act, which would provide middle class and working families with a tax credit of up to $6,000 a year - or up to $500 a month - to help address the rising cost of living. https://www.theatlantic.com/ideas/archive/2018/10/lefts-trump-sized-tax-plans/573328/", "time": "2018-10-18T12:30:31-04:00", "link": "https://www.twitter.com/SenKamalaHarris/statuses/1052960124900397056", "source": "Twitter Web Client"}, {"user_id": "30354991", "id": "1053062502697893888", "screen_name": "KamalaHarris", "text": "Everything from health care to gun safety reform is on the line in November. So don\u2019t just vote this year \u2014 volunteer! Go to http://thelastweekend.org to sign up. #TheLastWeekend http://pbs.twimg.com/ext_tw_video_thumb/1053062423274512384/pu/img/028eONM-_t1vOShA.jpg https://video.twimg.com/ext_tw_video/1053062423274512384/pu/vid/320x180/ra2kgzuyf3yzZa4d.mp4?tag=5", "time": "2018-10-18T19:17:20-04:00", "link": "https://www.twitter.com/KamalaHarris/statuses/1053062502697893888", "source": "Sprout Social"}, {"user_id": "23022687", "id": "1052920103984123904", "screen_name": "tedcruz", "text": "RT @redsteeze https://www.nbcnews.com/news/amp/ncna921391?__twitter_impression=true http://pbs.twimg.com/media/Dpy4IrcXcAABv3H.jpg", "time": "2018-10-18T09:51:29-04:00", "link": "https://www.twitter.com/redsteeze/statuses/1052918875946405894", "source": "Twitter for iPhone"}, {"user_id": "23022687", "id": "1053066850639269888", "screen_name": "tedcruz", "text": "Congressman O'Rourke's health care plan doesn\u2019t even pass elementary school math. #TXSen", "time": "2018-10-18T19:34:36-04:00", "link": "https://www.twitter.com/tedcruz/statuses/1053066850639269888", "source": "Twitter Ads Composer"}, {"user_id": "15808765", "id": "1052969094469828608", "screen_name": "CoryBooker", "text": "Excited and humbled to be the speaker for services at @ebenezer_atl, the pastoral home of Martin Luther King, Jr. in Atlanta this Sunday at 9am\u2014please join us if you're in the area!", "time": "2018-10-18T13:06:09-04:00", "link": "https://www.twitter.com/CoryBooker/statuses/1052969094469828608", "source": "Buffer"}, {"user_id": "23022687", "id": "1053031762077605889", "screen_name": "tedcruz", "text": "RT @ACUConservative \u201cSen. @tedcruz has been a champion of conservative principles and policies during his time in the Senate. He has a lifetime rating of 99% and has been a staunch defender of Life, the Second Amendment, and the Rule of Law,\" says @mschlapp.", "time": "2018-10-18T17:15:11-04:00", "link": "https://www.twitter.com/ACUConservative/statuses/1053030291135115264", "source": "TweetDeck"}, {"user_id": "229966028", "id": "1052938246135656458", "screen_name": "SenRubioPress", "text": "Hoy se cumplen 72 d\u00edas desde que el r\u00e9gimen de #Maduro captur\u00f3 arbitrariamente al Diputado @JuanRequesens. El r\u00e9gimen debe liberar a todos los presos pol\u00edticos, Maduro y sus secuaces son responsable del bienestar de TODOS los presos.", "time": "2018-10-18T11:03:35-04:00", "link": "https://www.twitter.com/SenRubioPress/statuses/1052938246135656458", "source": "Twitter Web Client"}, {"user_id": "29442313", "id": "1052995376461037568", "screen_name": "SenSanders", "text": "The crisis we face as a country is not because of voter fraud. It is because of voter suppression. If Republicans must intimidate and disenfranchise voters in order to win, then they should not be running for office in the first place.\nhttps://www.vox.com/identities/2018/10/17/17990110/georgia-senior-citizens-bus-removal-black-voters-matter-suppression", "time": "2018-10-18T14:50:36-04:00", "link": "https://www.twitter.com/SenSanders/statuses/1052995376461037568", "source": "Twitter Web Client"}, {"user_id": "30354991", "id": "1053007814732521473", "screen_name": "KamalaHarris", "text": "No one should be bullied or harassed because of their identity. This #SpiritDay, I\u2019m joining people across our nation who are taking a stand for LGBTQ youth. We have your back today and every day. http://pbs.twimg.com/media/Dp0JBnoWwAEYoc-.jpg", "time": "2018-10-18T15:40:01-04:00", "link": "https://www.twitter.com/KamalaHarris/statuses/1053007814732521473", "source": "Sprout Social"}, {"user_id": "23022687", "id": "1053063114927824898", "screen_name": "tedcruz", "text": "RT @tedcruz You saw last night\u2019s #TexasDebate.\n\nYou know the stakes of this race.\n\nNow we need YOUR help to #CruzToVictory on November 6th.\n\nPlease pitch in $5 or more now so we have the resources to WIN: https://secure.tedcruz.org/donate_tw5 #TXSen #ChooseCruz", "time": "2018-10-18T19:19:46-04:00", "link": "https://www.twitter.com/tedcruz/statuses/1052582845741330432", "source": "Twitter for iPhone"}, {"user_id": "15745368", "id": "1052937503651651584", "screen_name": "marcorubio", "text": ".@Uber is offering free rides to &amp; from shelters. Use code MICHAELSHELTER to receive free UberX &amp; UberXL trips to &amp; from any official Red Cross Shelter in #Florida until October 31, 2018.  Residents can travel for up to $25 per trip or up to 5 trips per user #Sayfie", "time": "2018-10-18T11:00:38-04:00", "link": "https://www.twitter.com/marcorubio/statuses/1052937503651651584", "source": "Twitter for iPad"}, {"user_id": "23022687", "id": "1053062419235385345", "screen_name": "tedcruz", "text": "RT @TeamTedCruz Congressman O\u2019Rourke voted NO on a resolution supporting the officers and personnel who carry out the important mission of the United States Immigration and Customs Enforcement:\n\n\u2014&gt; http://clerk.house.gov/evs/2018/roll337.xml \n\n\u2014&gt; https://www.congress.gov/bill/115th-congress/house-resolution/990 #TexasTownHall #TXSen", "time": "2018-10-18T19:17:00-04:00", "link": "https://www.twitter.com/TeamTedCruz/statuses/1053062339543601153", "source": "Twitter for iPhone"}, {"user_id": "39834947", "id": "1053031927769419777", "screen_name": "DrRandPaul", "text": "I had a great afternoon visiting neighbor West Virginia in support of @MorriseyWV. He has my full support. We discussed his opponent\u2019s BIG spending ways and love of sending taxpayer money overseas. Patrick is a great constitutional conservative! http://pbs.twimg.com/media/Dp0e7CtWsAQDZqQ.jpg http://pbs.twimg.com/media/Dp0e7CvW0AcWPnw.jpg http://pbs.twimg.com/media/Dp0e7CtW4AAvV9l.jpg http://pbs.twimg.com/media/Dp0e70FXgAAuUXt.jpg", "time": "2018-10-18T17:15:50-04:00", "link": "https://www.twitter.com/DrRandPaul/statuses/1053031927769419777", "source": "Twitter Web Client"}, {"user_id": "23022687", "id": "1053078976141422592", "screen_name": "tedcruz", "text": "RT @Frazier7324 Great visit and roundtable with @tedcruz . The narrative of supporting and backing law enforcement is one his opponent does not share. I represent law enforcement and will only vote for those who help promote and protect my profession and our LEO families. http://pbs.twimg.com/media/Dp09gUQUUAA0Qtz.jpg http://pbs.twimg.com/media/Dp09gUSVsAEtBSe.jpg", "time": "2018-10-18T20:22:47-04:00", "link": "https://www.twitter.com/Frazier7324/statuses/1053065524161249281", "source": "Twitter Web Client"}, {"user_id": "23022687", "id": "1053050109032849408", "screen_name": "tedcruz", "text": "RT @trscoop BOOM! Trump forced to UPGRADE to bigger rally for Ted\u00a0Cruz! https://therightscoop.com/boom-trump-forced-to-upgrade-to-bigger-rally-for-ted-cruz/ http://pbs.twimg.com/media/Dp0vU-wVAAAHaIB.jpg", "time": "2018-10-18T18:28:05-04:00", "link": "https://www.twitter.com/trscoop/statuses/1053049927474049024", "source": "Twitter for iPhone"}, {"user_id": "23022687", "id": "1053069465586348032", "screen_name": "tedcruz", "text": "Congressman O'Rourke voted in favor of a $10-a-barrel tax on Texas oil. #ChooseCruz #TXSen", "time": "2018-10-18T19:45:00-04:00", "link": "https://www.twitter.com/tedcruz/statuses/1053069465586348032", "source": "Twitter Ads Composer"}, {"user_id": "216776631", "id": "1052932233915506690", "screen_name": "BernieSanders", "text": "RT @gretchenwhitmer Join us on Friday for a rally with @BernieSanders!\n\nFor more details visit https://events.mobilizeamerica.io/whitmerformi/event/73795/ http://pbs.twimg.com/media/DplcFDpXgAAp6Pp.jpg", "time": "2018-10-18T10:39:41-04:00", "link": "https://www.twitter.com/gretchenwhitmer/statuses/1051973715003666432", "source": "Twitter Web Client"}, {"user_id": "23022687", "id": "1052954388308869122", "screen_name": "tedcruz", "text": "RT @SenTedCruz Yesterday while surveying flood damage visiting fellow Texans, I met a football coach from @MarbleFallsISD, who I can attest is a true embodiment of Texas\u2019 can-do spirit. In the face of disaster he remains resilient &amp; a supporter to his fellow Texans in need. #TexansHelpingTexans http://pbs.twimg.com/media/Dpy0NFhWkAAGzu6.jpg", "time": "2018-10-18T12:07:43-04:00", "link": "https://www.twitter.com/SenTedCruz/statuses/1052914553628106757", "source": "Twitter Web Client"}, {"user_id": "30354991", "id": "1053045811934834689", "screen_name": "KamalaHarris", "text": "Young voters will make a difference in this election. \nhttps://twitter.com/CharlotteAlter/status/1051919392605384704 QT @CharlotteAlter In 2016, they were old enough to pay attention but too young to vote. Here's how first-time voters-- who are 18 in 2018-- could affect the midterms\nhttp://time.com/5424872/midterm-elections-teen-voters-millennials/", "time": "2018-10-18T18:11:00-04:00", "link": "https://www.twitter.com/KamalaHarris/statuses/1053045811934834689", "source": "Sprout Social"}, {"user_id": "229966028", "id": "1052922105648566274", "screen_name": "SenRubioPress", "text": "RT @WMBBTV Senator Marco Rubio's staff will host mobile office hours in Gulf County today from 11 a.m. until 5 p.m. CT at the Honeyville Community Center in Wewahitchka for anyone needing federal or state assistance.", "time": "2018-10-18T09:59:26-04:00", "link": "https://www.twitter.com/WMBBTV/statuses/1052916302665474048", "source": "Twitter Web Client"}, {"user_id": "23022687", "id": "1052954351273209857", "screen_name": "tedcruz", "text": "RT @RepRWilliams .@SenTedCruz and I visited the site of the FM 2900 bridge that collapsed during the flooding in Kingsland, as well as with the folks in Marble Falls. Even though this flood has been absolutely devastating to Central TX community, Texans are tough &amp; together, we will rebuild. http://pbs.twimg.com/media/Dpv1VMZUwAEiUPL.jpg http://pbs.twimg.com/media/Dpv1VMZUUAYxB1d.jpg http://pbs.twimg.com/media/Dpv1VNUVsAAIdcu.jpg http://pbs.twimg.com/media/Dpv1VNVU4AAg2DM.jpg", "time": "2018-10-18T12:07:34-04:00", "link": "https://www.twitter.com/RepRWilliams/statuses/1052704705808347136", "source": "Twitter Web Client"}, {"user_id": "229966028", "id": "1052985857106472961", "screen_name": "SenRubioPress", "text": "El comportamiento de diplom\u00e1ticos #cubanos y #bolivianos en un evento de la @ONU_es,  el cual se centraba en mostrar la realidad que afrontan los presos pol\u00edticos en Cuba fue vergonzoso. Los foros internacionales son para la expresi\u00f3n, no para la intimidaci\u00f3n.", "time": "2018-10-18T14:12:46-04:00", "link": "https://www.twitter.com/SenRubioPress/statuses/1052985857106472961", "source": "Twitter Web Client"}, {"user_id": "23022687", "id": "1053095333062983680", "screen_name": "tedcruz", "text": "RT @tedcruz I'm LIVE with @MarkDavis on Facebook... join the conversation: https://www.facebook.com/tedcruzpage/videos/734661320231996/ #TXSen http://pbs.twimg.com/media/Dp1VFC3WoAARalW.jpg", "time": "2018-10-18T21:27:47-04:00", "link": "https://www.twitter.com/tedcruz/statuses/1053091714595020800", "source": "TweetDeck"}, {"user_id": "15808765", "id": "1053095279094849536", "screen_name": "CoryBooker", "text": "Senator Grassley is attacking my friend Rob Sand, a truly good man, running for state auditor in Iowa. If you are frustrated by that news, here's a good way to help Rob out: https://secure.actblue.com/donate/helprobokr#", "time": "2018-10-18T21:27:34-04:00", "link": "https://www.twitter.com/CoryBooker/statuses/1053095279094849536", "source": "Buffer"}, {"user_id": "216776631", "id": "1053017214939475969", "screen_name": "BernieSanders", "text": "You're literally working alongside 20 Republican attorneys general to end protections for people with preexisting conditions.\n\nNo one can estimate how many thousands of those people will die if you and your Republican friends are successful. https://twitter.com/realDonaldTrump/status/1053008701026693122 QT @realDonaldTrump All Republicans support people with pre-existing conditions, and if they don\u2019t, they will after I speak to them. I am in total support. Also, Democrats will destroy your Medicare, and I will keep it healthy and well!", "time": "2018-10-18T16:17:22-04:00", "link": "https://www.twitter.com/BernieSanders/statuses/1053017214939475969", "source": "Twitter Web Client"}, {"user_id": "216881337", "id": "1052988352406925314", "screen_name": "RandPaul", "text": "Yesterday I stopped in Maysville to discuss Kentucky\u2019s river industry. I chatted with the @MaysvilleNews about the visit and why it\u2019s important for me to hear from Kentuckians on important issues like our waterways. https://maysville-online.com/news/158503/sen-rand-paul-visits-maysville-to-discuss-river-industry", "time": "2018-10-18T14:22:41-04:00", "link": "https://www.twitter.com/RandPaul/statuses/1052988352406925314", "source": "Twitter for iPhone"}, {"user_id": "229966028", "id": "1052971942427459584", "screen_name": "SenRubioPress", "text": "This past Sunday on CNN, I urged Secretary Mnuchin not to attend an investment summit in #SaudiArabia. He made the right decision. The world needs to see America\u2019s leaders taking the disappearance and murder of #JamalKhashoggi seriously.", "time": "2018-10-18T13:17:29-04:00", "link": "https://www.twitter.com/SenRubioPress/statuses/1052971942427459584", "source": "Twitter Web Client"}, {"user_id": "23022687", "id": "1052917090468986881", "screen_name": "tedcruz", "text": "RT @FoxFriendsFirst Senator Ted Cruz harassed yet again by protesters over his support for Justice Kavanaugh. Do you think these protests are going too far? http://pbs.twimg.com/media/Dpx5EfpW4AAKBI7.jpg", "time": "2018-10-18T09:39:31-04:00", "link": "https://www.twitter.com/FoxFriendsFirst/statuses/1052849560714924033", "source": "Twitter for iPhone"}, {"user_id": "29442313", "id": "1053050634046337024", "screen_name": "SenSanders", "text": "The debate over climate change in Washington really has nothing to do with science. It has everything to do with campaign contributions. http://pbs.twimg.com/amplify_video_thumb/1053048850875854848/img/MZMm3kOSXv3ns8DU.jpg https://video.twimg.com/amplify_video/1053048850875854848/vid/240x240/8tMR7gZw7vbf91J9.mp4?tag=8", "time": "2018-10-18T18:30:10-04:00", "link": "https://www.twitter.com/SenSanders/statuses/1053050634046337024", "source": "Media Studio"}, {"user_id": "1379584350", "id": "1052937939502714880", "screen_name": "TeamTedCruz", "text": "RT @IngrahamAngle Texans want more, not less, economic growth.  They know a PR-spun, media-created candidate when they see one. #BetohNoYouDont #VoteCruz @realDonaldTrump @tedcruz http://pbs.twimg.com/media/DpzCJ9wXcAAz4NK.jpg", "time": "2018-10-18T11:02:22-04:00", "link": "https://www.twitter.com/IngrahamAngle/statuses/1052930436228403201", "source": "TweetDeck"}, {"user_id": "1074480192", "id": "1052914553628106757", "screen_name": "SenTedCruz", "text": "Yesterday while surveying flood damage visiting fellow Texans, I met a football coach from @MarbleFallsISD, who I can attest is a true embodiment of Texas\u2019 can-do spirit. In the face of disaster he remains resilient &amp; a supporter to his fellow Texans in need. #TexansHelpingTexans http://pbs.twimg.com/media/Dpy0NFhWkAAGzu6.jpg", "time": "2018-10-18T09:29:26-04:00", "link": "https://www.twitter.com/SenTedCruz/statuses/1052914553628106757", "source": "Twitter for iPhone"}, {"user_id": "23022687", "id": "1053058140701257728", "screen_name": "tedcruz", "text": "WATCH: Congressman O'Rourke's health care plan would bankrupt Medicare for those who need it! #ChooseCruz #TXSen", "time": "2018-10-18T19:00:00-04:00", "link": "https://www.twitter.com/tedcruz/statuses/1053058140701257728", "source": "Twitter Ads Composer"}, {"user_id": "30354991", "id": "1052974533983031301", "screen_name": "KamalaHarris", "text": "One survey found that 57% of Americans don\u2019t have enough cash for a $500 emergency cost. I\u2019ve announced a plan to help middle-class and working Americans with the rising cost of living. Read more about my LIFT Act. \nhttps://www.theatlantic.com/ideas/archive/2018/10/lefts-trump-sized-tax-plans/573328/", "time": "2018-10-18T13:27:46-04:00", "link": "https://www.twitter.com/KamalaHarris/statuses/1052974533983031301", "source": "Sprout Social"}, {"user_id": "23022687", "id": "1053124822635634688", "screen_name": "tedcruz", "text": "RT @TheRightScoop BOOM! Trump forced to UPGRADE to bigger rally for Ted\u00a0Cruz! https://therightscoop.com/boom-trump-forced-to-upgrade-to-bigger-rally-for-ted-cruz/ http://pbs.twimg.com/media/Dp0vVoyVYAA4bU3.jpg", "time": "2018-10-18T23:24:58-04:00", "link": "https://www.twitter.com/TheRightScoop/statuses/1053049938689642496", "source": "Twitter for iPhone"}, {"user_id": "229966028", "id": "1052985779817988096", "screen_name": "SenRubioPress", "text": "The disruptive behavior by #Cuban and #Bolivian diplomats at a @UN event that was intended to shine a light on the reality faced by political prisoners in Cuba was disgraceful. International Forums are for expression, not intimidation and bullying.", "time": "2018-10-18T14:12:28-04:00", "link": "https://www.twitter.com/SenRubioPress/statuses/1052985779817988096", "source": "Twitter Web Client"}, {"user_id": "23022687", "id": "1052926390868344838", "screen_name": "tedcruz", "text": "A $10 dollar-a-barrel tax on Texas oil is not good for Texas. #ChooseCruz #TXSen", "time": "2018-10-18T10:16:28-04:00", "link": "https://www.twitter.com/tedcruz/statuses/1052926390868344838", "source": "Twitter Ads Composer"}, {"user_id": "23022687", "id": "1053070114881503235", "screen_name": "tedcruz", "text": "Congressman O'Rourke voted in favor of taxing Texas oil $10 a barrel.\n\nThat means YOU would pay 24 cents more per gallon at the pump. #TXSen #TexasTownHall", "time": "2018-10-18T19:47:35-04:00", "link": "https://www.twitter.com/tedcruz/statuses/1053070114881503235", "source": "Twitter Ads Composer"}, {"user_id": "23022687", "id": "1053133606472871936", "screen_name": "tedcruz", "text": "Would 2 years of impeachment madness \u2014 a partisan circus that would utterly paralyze the federal govt \u2014 be good for Texans? I say NO. Beto (the only Dem Senate nominee in the country willing to do so) says YES, impeach President Trump. Listen, in his own words, and you decide. https://twitter.com/Breaking911/status/1053069105635475456 QT @Breaking911 Texas Democrat Beto O'Rourke says he supports impeaching President Trump\n\nhttp://pbs.twimg.com/media/Dp09mdBV4AAOC6D.jpg https://video.twimg.com/amplify_video/1053065331248222208/vid/320x180/7wON_fhXMC4MpI0v.mp4?tag=8", "time": "2018-10-18T23:59:52-04:00", "link": "https://www.twitter.com/tedcruz/statuses/1053133606472871936", "source": "Twitter for iPhone"}, {"user_id": "29442313", "id": "1052963643288117248", "screen_name": "SenSanders", "text": "The president makes it more and more clear with every authoritarian he meets that he not only admires them but wants to follow their lead. http://pbs.twimg.com/media/DpzgvFTXgAEls_6.jpg https://video.twimg.com/amplify_video/1052940432253046785/vid/240x240/AYjIJjd9p2JEtZef.mp4?tag=8", "time": "2018-10-18T12:44:30-04:00", "link": "https://www.twitter.com/SenSanders/statuses/1052963643288117248", "source": "Media Studio"}, {"user_id": "216881337", "id": "1053022869985390592", "screen_name": "RandPaul", "text": "RT @KelleyAshbyPaul Thank you to President Donna Davidson for hosting me at WROCK\u2019s luncheon today.  State Representative @lynnbechler dropped by to say hello. He\u2019s doing great in western Kentucky. I\u2019m proud of how our state legislature is leading the way on some criminal justice reform bills. http://pbs.twimg.com/media/Dp0V8fVX4AI7av3.jpg http://pbs.twimg.com/media/Dp0WALnXgAArJ2t.jpg http://pbs.twimg.com/media/Dp0WCP6XoAcVDRe.jpg http://pbs.twimg.com/media/Dp0WCQJWkAAdbJR.jpg", "time": "2018-10-18T16:39:51-04:00", "link": "https://www.twitter.com/KelleyAshbyPaul/statuses/1053022726745677825", "source": "Twitter for iPhone"}, {"user_id": "23022687", "id": "1053025744664911872", "screen_name": "tedcruz", "text": "RT @TexasTribune Donald Trump's Houston rally with @tedcruz has been moved to a bigger venue. #txsen https://www.texastribune.org/2018/10/18/donald-trumps-houston-rally-ted-cruz-moved-bigger-venue/?utm_campaign=trib-social&utm_medium=social&utm_source=twitter&utm_content=1539894973", "time": "2018-10-18T16:51:16-04:00", "link": "https://www.twitter.com/TexasTribune/statuses/1053023019864600577", "source": "Twitter for iPhone"}, {"user_id": "15745368", "id": "1052937498618462208", "screen_name": "marcorubio", "text": "National Dislocated Worker Grant funding is available to help #Florida assess workforce needs due to significant job losses caused by Hurricane. This funding assists the state &amp; local governments expand service capacity of dislocated worker training &amp; employment programs #Sayfie", "time": "2018-10-18T11:00:36-04:00", "link": "https://www.twitter.com/marcorubio/statuses/1052937498618462208", "source": "Twitter for iPad"}, {"user_id": "216776631", "id": "1053127511503192064", "screen_name": "BernieSanders", "text": "RT @LizForIndiana Friday at 11 am in Dunn Meadow in BLOOMINGTON! http://pbs.twimg.com/media/Dpwf5bTXgAAbs-I.jpg", "time": "2018-10-18T23:35:39-04:00", "link": "https://www.twitter.com/LizForIndiana/statuses/1052751488802525184", "source": "Twitter Web Client"}, {"user_id": "15745368", "id": "1052937501206372352", "screen_name": "marcorubio", "text": ".@DeptVetAffairs has activated the National Pharmaceutical Pharmacy Disaster Network Plan.  Veterans impacted by Hurricane who require an emergency supply of medications can access retail pharmacies. Call 1-855-574-7288 for more information #Sayfie", "time": "2018-10-18T11:00:37-04:00", "link": "https://www.twitter.com/marcorubio/statuses/1052937501206372352", "source": "Twitter for iPad"}, {"user_id": "216776631", "id": "1053018220423274498", "screen_name": "BernieSanders", "text": "I'm hitting the road again because this is the most important midterm election in our lifetimes. Let's work together to end one-party rule in Washington. http://pbs.twimg.com/amplify_video_thumb/1053016709005799425/img/M9wN00IreQkArmbM.jpg https://video.twimg.com/amplify_video/1053016709005799425/vid/240x240/pwxxqX7MUDLTZiJa.mp4?tag=8", "time": "2018-10-18T16:21:22-04:00", "link": "https://www.twitter.com/BernieSanders/statuses/1053018220423274498", "source": "Media Studio"}, {"user_id": "803694179079458816", "id": "1052970089199353858", "screen_name": "SenKamalaHarris", "text": "Today I encourage all Californians to participate in the Great #ShakeOut Earthquake Drill at 10:18 AM local time. To learn more about how to protect yourself during an earthquake, visit http://www.ShakeOut.org.", "time": "2018-10-18T13:10:07-04:00", "link": "https://www.twitter.com/SenKamalaHarris/statuses/1052970089199353858", "source": "Sprout Social"}, {"user_id": "23022687", "id": "1053066424854417408", "screen_name": "tedcruz", "text": "Now vs then... #TXSen", "time": "2018-10-18T19:32:55-04:00", "link": "https://www.twitter.com/tedcruz/statuses/1053066424854417408", "source": "Twitter Ads Composer"}, {"user_id": "30354991", "id": "1053031470275710981", "screen_name": "KamalaHarris", "text": "Our tax code should reflect our values. It\u2019s estimated the LIFT Act would impact 1 in every 2 American workers and 2 out of 3 children.  \n\n\u201cThe Center on Budget and Policy Priorities calculating that the proposal would lift 9M people out of poverty, including nearly 3M kids.\" https://twitter.com/AnnieLowrey/status/1052916605922025473 QT @AnnieLowrey Kamala Harris wants to give working families as much as $500 a month in cash. Me on the Democrats' Trump-sized tax plans: https://www.theatlantic.com/ideas/archive/2018/10/lefts-trump-sized-tax-plans/573328/", "time": "2018-10-18T17:14:01-04:00", "link": "https://www.twitter.com/KamalaHarris/statuses/1053031470275710981", "source": "Sprout Social"}, {"user_id": "30354991", "id": "1053083306722504704", "screen_name": "KamalaHarris", "text": "We must make it easier to vote in this country. Full stop. Everyone deserves to have easy access to the ballot box.\nhttps://twitter.com/ben_brasch/status/1052571889762295810 QT @ben_brasch There\u2019s an estimated wait of 3 hours to vote early for the midterms in Cobb, one of Georgia\u2019s largest counties. Janine Eveler, head of Cobb elections, said some people lined up at 7 a.m. \u2014 the polls open at 8 a.m. @CobbNewsNow @ajc @PoliticallyGa http://pbs.twimg.com/ext_tw_video_thumb/1052571841825525760/pu/img/Y9tdQEikn7XLsbdv.jpg https://video.twimg.com/ext_tw_video/1052571841825525760/pu/vid/320x180/U5Yq9qsP720HfrKJ.mp4?tag=5", "time": "2018-10-18T20:40:00-04:00", "link": "https://www.twitter.com/KamalaHarris/statuses/1053083306722504704", "source": "Sprout Social"}, {"user_id": "23022687", "id": "1053063150508167168", "screen_name": "tedcruz", "text": "RT @tedcruz WATCH: Congressman O'Rourke's health care plan would bankrupt Medicare for those who need it! #ChooseCruz #TXSen", "time": "2018-10-18T19:19:54-04:00", "link": "https://www.twitter.com/tedcruz/statuses/1053058140701257728", "source": "Twitter for iPhone"}, {"user_id": "970207298", "id": "1052949211967365120", "screen_name": "SenWarren", "text": ".@WellsFargo CEO Tim Sloan was a senior manager during the bank\u2019s fake accounts scam &amp; other scandals. How can Wells clean up its act while he\u2019s still in charge? The @FederalReserve shouldn\u2019t lift its growth restriction on the bank until Sloan is fired. https://www.thestreet.com/markets/wells-fargo-ceo-must-go-senator-warren-tells-fed-chairman-powell-14749692", "time": "2018-10-18T11:47:09-04:00", "link": "https://www.twitter.com/SenWarren/statuses/1052949211967365120", "source": "Twitter Web Client"}, {"user_id": "15745368", "id": "1052937485465071616", "screen_name": "marcorubio", "text": "Latest updates on federal response to #HurricaneMichael in the thread below: #Sayfie", "time": "2018-10-18T11:00:33-04:00", "link": "https://www.twitter.com/marcorubio/statuses/1052937485465071616", "source": "Twitter for iPad"}, {"user_id": "23022687", "id": "1052954337352265728", "screen_name": "tedcruz", "text": "RT @SenTedCruz Thank you to Judge Oakley for providing a briefing on the communities in Burnet County that have been impacted by the recent flooding of the Llano River. Grateful for the work he &amp; his @highlandlakestx team have done to help our fellow Texans that have been affected by the flood. http://pbs.twimg.com/media/DpveewiW0AMqM3Z.jpg http://pbs.twimg.com/media/DpveewnW0AE8FPn.jpg http://pbs.twimg.com/media/DpveewkWwAAs3rS.jpg", "time": "2018-10-18T12:07:31-04:00", "link": "https://www.twitter.com/SenTedCruz/statuses/1052679675833671680", "source": "Twitter Web Client"}, {"user_id": "30354991", "id": "1053102686504185856", "screen_name": "KamalaHarris", "text": "Congress gave more than a trillion dollars in tax breaks to corporations &amp; the top 1% last year. That money should have gone to American taxpayers who need it. The LIFT Act I'm proposing would fix this and address the rising cost of living.\nhttps://www.theatlantic.com/ideas/archive/2018/10/lefts-trump-sized-tax-plans/573328/", "time": "2018-10-18T21:57:00-04:00", "link": "https://www.twitter.com/KamalaHarris/statuses/1053102686504185856", "source": "Sprout Social"}, {"user_id": "15745368", "id": "1052937491009933315", "screen_name": "marcorubio", "text": "Homeowners in 12 counties impacted by Hurricane now eligible for temporary repairs under #OperationBlueRoof from @FEMA &amp; @USACEHQ. Operations have begun in Bay County &amp; those in 11 other counties can apply at https://www.usace.army.mil/blueroof or in person at ROE centers set up area #Sayfie", "time": "2018-10-18T11:00:35-04:00", "link": "https://www.twitter.com/marcorubio/statuses/1052937491009933315", "source": "Twitter for iPad"}, {"user_id": "1074480192", "id": "1052990655507648513", "screen_name": "SenTedCruz", "text": "Grateful for Texas' law enforcement and first responders for helping Texans in Burnet &amp; Llano County evacuate during the recent flooding of the Llano River. http://pbs.twimg.com/ext_tw_video_thumb/1052990612969013251/pu/img/pMrrEu-wh_k4ymMZ.jpg https://video.twimg.com/ext_tw_video/1052990612969013251/pu/vid/320x180/MRELSonr0x5WVRZQ.mp4?tag=5", "time": "2018-10-18T14:31:50-04:00", "link": "https://www.twitter.com/SenTedCruz/statuses/1052990655507648513", "source": "Twitter Lite"}, {"user_id": "216881337", "id": "1052903228508200960", "screen_name": "RandPaul", "text": "Soros paid protester arrested.  Same group operates inside congressional office buildings. Are democrats paying to incite violence? https://www.foxnews.com/politics/soros-backed-group-fires-operative-after-arrest-over-alleged-battery-against-gop-campaign-manager", "time": "2018-10-18T08:44:26-04:00", "link": "https://www.twitter.com/RandPaul/statuses/1052903228508200960", "source": "Twitter for iPhone"}, {"user_id": "23022687", "id": "1053048500563390465", "screen_name": "tedcruz", "text": "RT @cathieadams TEXAS DEBATE: Sen. Cruz says voters should choose hope and vote for him ... https://youtu.be/ghM-HWi79i8 via @YouTube", "time": "2018-10-18T18:21:41-04:00", "link": "https://www.twitter.com/cathieadams/statuses/1053048382590275585", "source": "TweetDeck"}, {"user_id": "15745368", "id": "1052937505333497858", "screen_name": "marcorubio", "text": ".@verizon has 2 free charging stations in #Marianna &amp; 2 in #PanamaCity #Florida. Also have Big Red Command Trailer with  multiple workstations &amp; satellite connectivity &amp; is supporting emergency personnel at #BayCounty EOC Emergency Operations Center #Sayfie", "time": "2018-10-18T11:00:38-04:00", "link": "https://www.twitter.com/marcorubio/statuses/1052937505333497858", "source": "Twitter for iPad"}, {"user_id": "23022687", "id": "1052954322588319744", "screen_name": "tedcruz", "text": "RT @SenTedCruz Sen. Ted Cruz, other Texas leaders to speak at washed away 2900 bridge in Kingsland https://cbsaustin.com/news/local/sen-ted-cruz-other-texas-leaders-to-speak-at-washed-away-2900-bridge-in-kingsland", "time": "2018-10-18T12:07:28-04:00", "link": "https://www.twitter.com/SenTedCruz/statuses/1052657064743497729", "source": "Twitter Web Client"}]