[{"user_id": "229966028", "id": "1094003150745464834", "screen_name": "SenRubioPress", "text": "Today, I joined @TurtleHosp to personally release a rescued and rehabilitated sea turtle. What an unforgettable experience! #sayfie http://pbs.twimg.com/media/Dy6uCV3X4AAKLSf.jpg http://pbs.twimg.com/media/Dy6uCWkX0AEgatz.jpg http://pbs.twimg.com/media/Dy6uCWjXQAA7bZF.jpg", "time": "2019-02-08T17:40:51-05:00", "link": "https://www.twitter.com/SenRubioPress/statuses/1094003150745464834", "source": "Twitter Web Client"}, {"user_id": "803694179079458816", "id": "1093963930072944646", "screen_name": "SenKamalaHarris", "text": "Yesterday Republicans advanced 44 of Trump's nominees to lifetime federal court seats - nominees who have expressed views that are contrary to many of our foundational values of justice and equality. We all need to pay attention to what this Administration is doing to our courts. http://pbs.twimg.com/amplify_video_thumb/1093962840413794310/img/jNVW7M8EUxLoCPHg.jpg https://video.twimg.com/amplify_video/1093962840413794310/vid/320x180/VrkimrqHqQ5c-2qa.mp4?tag=9", "time": "2019-02-08T15:05:00-05:00", "link": "https://www.twitter.com/SenKamalaHarris/statuses/1093963930072944646", "source": "Twitter Media Studio"}, {"user_id": "138203134", "id": "1093921428452360193", "screen_name": "AOC", "text": "Can everyday people come together and effectively organize against creeping overreach of one of the world\u2019s biggest corporations?\n\nYes, they can.\nhttps://www.washingtonpost.com/local/virginia-politics/facing-opposition-amazon-reconsiders-ny-headquarters-site-two-officials-say/2019/02/08/451ffc52-2a19-11e9-b011-d8500644dc98_story.html?noredirect=on&utm_term=.fd16bacfc982", "time": "2019-02-08T12:16:07-05:00", "link": "https://www.twitter.com/AOC/statuses/1093921428452360193", "source": "Twitter for iPhone"}, {"user_id": "229966028", "id": "1093872934798721024", "screen_name": "SenRubioPress", "text": "RT @SmallBizCmte Chairman @marcorubio, named Haynes Security Services, Inc. as the U.S. Senate Small Business of the Week. #smallbiz #sayfie http://pbs.twimg.com/ext_tw_video_thumb/1093871773970501632/pu/img/woqwvQu3ToxvHLC3.jpg https://video.twimg.com/ext_tw_video/1093871773970501632/pu/vid/320x180/vTMXq6ZdETdPDXLl.mp4?tag=6", "time": "2019-02-08T09:03:25-05:00", "link": "https://www.twitter.com/SmallBizCmte/statuses/1093872563741249536", "source": "Twitter Web Client"}, {"user_id": "229966028", "id": "1094002887712227331", "screen_name": "SenRubioPress", "text": "I never turn down an opportunity to get out on the water, but my time today with @NOAA and Sup. Fangman in the @FloridaKeysNMS was special. Working to ensure next week\u2019s funding bill maintains critical resources I championed for Florida\u2019s reefs. #sayfie http://pbs.twimg.com/media/Dy6t0dbWoAAnbjl.jpg", "time": "2019-02-08T17:39:48-05:00", "link": "https://www.twitter.com/SenRubioPress/statuses/1094002887712227331", "source": "Twitter Web Client"}, {"user_id": "29442313", "id": "1093919758825807879", "screen_name": "SenSanders", "text": "Trump's top intelligence officials, European allies, national security and nonproliferation experts: The Iran nuclear deal works.\n\nTrump: No. http://pbs.twimg.com/amplify_video_thumb/1093918433065029633/img/C-kM4Qb0zBACOIkb.jpg https://video.twimg.com/amplify_video/1093918433065029633/vid/320x320/NglBhVYV7trh4rrB.mp4?tag=9", "time": "2019-02-08T12:09:29-05:00", "link": "https://www.twitter.com/SenSanders/statuses/1093919758825807879", "source": "Twitter Media Studio"}, {"user_id": "229966028", "id": "1094004990274879488", "screen_name": "SenRubioPress", "text": ".@RadioFreeAsia reports PRC secretly moving large numbers of #Uyghurs &amp; other Muslims to prisons outside Xinjiang. After two years of revelations on mass internments in Xinjiang, why hasn\u2019t USG sanctioned any Chinese Govt or Communist Party officials https://www.rfa.org/english/news/uyghur/detainees-02072019190912.html", "time": "2019-02-08T17:48:09-05:00", "link": "https://www.twitter.com/SenRubioPress/statuses/1094004990274879488", "source": "Twitter Web Client"}, {"user_id": "15808765", "id": "1093940400765763584", "screen_name": "CoryBooker", "text": "RT @StopBigMoney What @CoryBooker said! http://pbs.twimg.com/ext_tw_video_thumb/1093903001994125312/pu/img/0gYUHT7H85mOX7pm.jpg https://video.twimg.com/ext_tw_video/1093903001994125312/pu/vid/320x180/z32aN-z0RMf_59Js.mp4?tag=6", "time": "2019-02-08T13:31:30-05:00", "link": "https://www.twitter.com/StopBigMoney/statuses/1093903113549959168", "source": "Twitter Web Client"}, {"user_id": "1074480192", "id": "1093915335709859840", "screen_name": "SenTedCruz", "text": "RT @SenTedCruz China trying to infiltrate US colleges to recruit spies, indoctrinate students, intelligence agencies say https://www.foxnews.com/us/china-infiltrating-us-colleges-to-recruit-spies-indoctrinate-students-intelligence-agencies-say #FoxNews", "time": "2019-02-08T11:51:54-05:00", "link": "https://www.twitter.com/SenTedCruz/statuses/1093553773593669632", "source": "Twitter Web Client"}, {"user_id": "30354991", "id": "1093970243339333634", "screen_name": "KamalaHarris", "text": "This Administration is protecting payday lenders over vulnerable Americans. That\u2019s wrong. Consumers deserve a government that fights to protect them.\nhttps://www.nbcnews.com/news/us-news/cfpb-announces-it-will-roll-back-obama-era-restrictions-payday-n968471", "time": "2019-02-08T15:30:05-05:00", "link": "https://www.twitter.com/KamalaHarris/statuses/1093970243339333634", "source": "Sprout Social"}, {"user_id": "29442313", "id": "1094030115724541952", "screen_name": "SenSanders", "text": "President Trump. Do not shut down the government again. Another Trump shutdown would be not only harmful to our federal workers, but also to the safety and security of our nation. http://pbs.twimg.com/amplify_video_thumb/1093918530414743553/img/bERcF7j8ubSGR-Ku.jpg https://video.twimg.com/amplify_video/1093918530414743553/vid/320x320/pIgvThGHPt7NU5dc.mp4?tag=9", "time": "2019-02-08T19:28:00-05:00", "link": "https://www.twitter.com/SenSanders/statuses/1094030115724541952", "source": "Twitter Media Studio"}, {"user_id": "30354991", "id": "1093905423990751233", "screen_name": "KamalaHarris", "text": "The Green New Deal is a bold plan to shift our country to 100% clean and renewable energy. We do not fight this fight for our generation alone\u200a but for generations to come.\nhttps://medium.com/@KamalaHarris/green-new-deal-2699b33ba666", "time": "2019-02-08T11:12:31-05:00", "link": "https://www.twitter.com/KamalaHarris/statuses/1093905423990751233", "source": "Sprout Social"}, {"user_id": "357606935", "id": "1094046582486519809", "screen_name": "ewarren", "text": "Can\u2019t join us in person in Lawrence? Sign up for updates on how you can watch our big event live tomorrow from wherever you are: https://my.elizabethwarren.com/page/s/watch-elizabeth-s-announcement-in-lawrence-?source=20190208tw", "time": "2019-02-08T20:33:26-05:00", "link": "https://www.twitter.com/ewarren/statuses/1094046582486519809", "source": "Twitter Web Client"}, {"user_id": "30354991", "id": "1093926403345735680", "screen_name": "KamalaHarris", "text": "The history of the civil rights movement is marked by the heroism of everyday people whose peaceful courage was too often met with violence. These three teenagers, along with the 28 others who were injured, remind us that justice is always worth fighting for.", "time": "2019-02-08T12:35:53-05:00", "link": "https://www.twitter.com/KamalaHarris/statuses/1093926403345735680", "source": "Twitter Web Client"}, {"user_id": "15745368", "id": "1093897269315809280", "screen_name": "marcorubio", "text": "The only one politicizing humanitarian aid is #Maduro. He uses access to food &amp; medicine as tool to control people.\n\nI hope the media will cover this as a crime not as a political struggle. Because providing food &amp; medicine is not political. https://www.washingtonpost.com/world/the_americas/tensions-escalate-over-delivery-of-humanitarian-aid-to-venezuela/2019/02/07/55b692ac-2ae0-11e9-906e-9d55b6451eb4_story.html", "time": "2019-02-08T10:40:07-05:00", "link": "https://www.twitter.com/marcorubio/statuses/1093897269315809280", "source": "Twitter for iPad"}, {"user_id": "15745368", "id": "1093857179365462017", "screen_name": "marcorubio", "text": "The LORD is my light and my salvation; whom should I fear? The LORD is my life\u2019s refuge; of whom should I be afraid?\n\nPsalms 27:1", "time": "2019-02-08T08:00:49-05:00", "link": "https://www.twitter.com/marcorubio/statuses/1093857179365462017", "source": "Twitter for iPad"}, {"user_id": "803694179079458816", "id": "1093932325438664704", "screen_name": "SenKamalaHarris", "text": "The reality is that climate change is an existential threat to our planet and we need bold change to combat it. Yesterday I was proud to join my colleagues to introduce a Green New Deal resolution. https://www.newyorker.com/news/our-columnists/with-the-green-new-deal-democrats-present-a-radical-proposition-for-combatting-climate-change", "time": "2019-02-08T12:59:25-05:00", "link": "https://www.twitter.com/SenKamalaHarris/statuses/1093932325438664704", "source": "Twitter Web Client"}, {"user_id": "229966028", "id": "1093959623810473985", "screen_name": "SenRubioPress", "text": "RT @Heritage MONDAY: Please join us with @IRIglobal for a conversation about Venezuela with Sen. @marcorubio\n\nRSVP: https://www.heritage.org/global-politics/event/venezuela-tipping-point?utm_medium=social&utm_source=twitter&utm_campaign=thf-tw\n\nPRESS: DM @GScottSays", "time": "2019-02-08T14:47:53-05:00", "link": "https://www.twitter.com/Heritage/statuses/1093953961873293315", "source": "Twitter Web Client"}, {"user_id": "357606935", "id": "1093998195259121664", "screen_name": "ewarren", "text": "Access to safe, legal abortion in Louisiana is protected for now, but Brett Kavanaugh\u2019s dissent reminds us: Roe v. Wade is under attack.\n\nWe stood up to Kavanaugh once, and we\u2019ll do it again. We won\u2019t go back \u2014 not now, not ever. https://slate.com/news-and-politics/2019/02/brett-kavanaugh-june-medical-services-louisiana-john-roberts.html", "time": "2019-02-08T17:21:09-05:00", "link": "https://www.twitter.com/ewarren/statuses/1093998195259121664", "source": "Twitter Web Client"}, {"user_id": "1074480192", "id": "1093879210970660865", "screen_name": "SenTedCruz", "text": "Sad to see Dems yet again try to derail a well-qualified nominee to serve our country bc they are terrified of their radical left wing base. William Barr previously served as a competent &amp; capable AG &amp; I'm confident that when confirmed he will once again ably serve our nation.", "time": "2019-02-08T09:28:21-05:00", "link": "https://www.twitter.com/SenTedCruz/statuses/1093879210970660865", "source": "Twitter Ads Composer"}, {"user_id": "29442313", "id": "1094018956195753985", "screen_name": "SenSanders", "text": "Donald Trump\u2019s relentless attacks on our political institutions not only undermine our democracy, they also embolden authoritarian leaders around the world. http://pbs.twimg.com/media/Dy68N7aVsAARN9g.jpg", "time": "2019-02-08T18:43:39-05:00", "link": "https://www.twitter.com/SenSanders/statuses/1094018956195753985", "source": "Twitter Web Client"}, {"user_id": "216776631", "id": "1093954677694177284", "screen_name": "BernieSanders", "text": "The mark of a great nation is judged not by how many tax breaks it can give to billionaires, but by how it treats its most vulnerable people.", "time": "2019-02-08T14:28:14-05:00", "link": "https://www.twitter.com/BernieSanders/statuses/1093954677694177284", "source": "Twitter for iPhone"}, {"user_id": "15745368", "id": "1093869016635052032", "screen_name": "marcorubio", "text": "I was hopeful we would be able to redefine the U.S.-Mexico relationship as a strategic partnership. \n\nNot a U.S. aid relationship.\n\nAn alliance to address our common challenges. \n\nBut the new government\u2019s inexplicable support for Maduro has put all of that in doubt.", "time": "2019-02-08T08:47:51-05:00", "link": "https://www.twitter.com/marcorubio/statuses/1093869016635052032", "source": "Twitter for iPad"}, {"user_id": "229966028", "id": "1093923387175591937", "screen_name": "SenRubioPress", "text": "RT @marcorubio First visited canals in #MarathonFlorida right after #HurricaneIrma. Then went to D.C. to get the $ to clean them up.\n\nVisited a 2nd time when work began on clean up.\n\nToday came for the 3rd time. 142 of 172 canals have been cleared of debris. \n\n#Sayfie http://pbs.twimg.com/media/Dy5jTXMW0AAFApm.jpg http://pbs.twimg.com/media/Dy5jTW6X0AAMN7Y.jpg", "time": "2019-02-08T12:23:54-05:00", "link": "https://www.twitter.com/marcorubio/statuses/1093920973731127296", "source": "Twitter Web Client"}, {"user_id": "970207298", "id": "1093909943042871296", "screen_name": "SenWarren", "text": "Gigantic banks wrecked our economy, but the Fed told me they are rubber-stamping nearly every proposed bank merger. @SunTrust and @BBT are probably next. We can\u2019t let banks become too big to fail again: American families will suffer. https://www.nytimes.com/2019/02/07/business/dealbook/bbt-suntrust-bank-mergers.html", "time": "2019-02-08T11:30:28-05:00", "link": "https://www.twitter.com/SenWarren/statuses/1093909943042871296", "source": "Twitter Web Client"}, {"user_id": "15808765", "id": "1093947470013497347", "screen_name": "CoryBooker", "text": "RT @harrisonjaime I know the American Dream is possible because I\u2019ve lived it. I want to help open doors of opportunity for all of our children. That\u2019s why I\u2019ve launched an exploratory committee to run for U.S. Senate against Lindsey Graham. Will you join us? #JoinJaime https://www.youtube.com/watch?v=hX2PKlmFie8&feature=youtu.be", "time": "2019-02-08T13:59:36-05:00", "link": "https://www.twitter.com/harrisonjaime/statuses/1093876336022773760", "source": "Twitter for iPhone"}, {"user_id": "138203134", "id": "1094066711819706369", "screen_name": "AOC", "text": "RT @ndrew_lawrence Watch what happens when Tucker Carlson steps out of the conservative bubble and brings on an @AOC policy adviser who debunks all the conservative media lies straight to his face  (spoiler: it doesn't go great for Tucker) http://pbs.twimg.com/ext_tw_video_thumb/1094046275513786375/pu/img/eXuUjgmovF08BWCv.jpg https://video.twimg.com/ext_tw_video/1094046275513786375/pu/vid/320x180/D-JWs-Sg1MIf3VTi.mp4?tag=6", "time": "2019-02-08T21:53:25-05:00", "link": "https://www.twitter.com/ndrew_lawrence/statuses/1094046349329338369", "source": "Twitter for iPhone"}, {"user_id": "216776631", "id": "1093995444085186560", "screen_name": "BernieSanders", "text": "While the ruling class may have the money, we have something that is even more powerful on our side \u2013 the people. Our government belongs to all of us, and not just the one percent.", "time": "2019-02-08T17:10:13-05:00", "link": "https://www.twitter.com/BernieSanders/statuses/1093995444085186560", "source": "Twitter for iPhone"}, {"user_id": "138203134", "id": "1093878740071972864", "screen_name": "AOC", "text": "RT @IlhanMN She is me, I am her!\n\n\u2764\ufe0f\u270a\ud83c\udffd @AOC https://twitter.com/reuterspictures/status/1093585687473999874 QT @reuterspictures Rep. Alexandria Ocasio-Cortez wipes away tears as Rep. Ilhan Omar talks about her own experience as a refugee during a news conference to call on Congress to cut funding for ICE. More photos of the day: https://www.reuters.com/news/picture/editors-choice-pictures-idUSRTX6LOAI \ud83d\udcf7 Jonathan Ernst http://pbs.twimg.com/media/Dy0lc-cXQAUubOA.jpg", "time": "2019-02-08T09:26:29-05:00", "link": "https://www.twitter.com/IlhanMN/statuses/1093720987827347456", "source": "Twitter for iPhone"}, {"user_id": "803694179079458816", "id": "1093916551428878336", "screen_name": "SenKamalaHarris", "text": "It's so important that sexual assault survivors have access to comprehensive &amp; responsive health care services. That's why my colleagues &amp; I recently introduced a bill to expand access to care for survivors &amp; gather data on how to improve the care they receive.", "time": "2019-02-08T11:56:44-05:00", "link": "https://www.twitter.com/SenKamalaHarris/statuses/1093916551428878336", "source": "Twitter Web Client"}, {"user_id": "138203134", "id": "1093961367768498176", "screen_name": "AOC", "text": "RT @nowthisnews Rep. @AOC is calling on Congress to cut funding to ICE and Border Patrol until they end their abusive treatment of immigrants http://pbs.twimg.com/amplify_video_thumb/1093565071685443585/img/_jWp0poSw3ogx1UZ.jpg https://video.twimg.com/amplify_video/1093565071685443585/vid/320x320/M6vbzNrrZrk4N3Qa.mp4?tag=9", "time": "2019-02-08T14:54:49-05:00", "link": "https://www.twitter.com/nowthisnews/statuses/1093960909590917120", "source": "Twitter for iPhone"}, {"user_id": "357606935", "id": "1094015645895835655", "screen_name": "ewarren", "text": "These credible and troubling allegations from Dr. Vanessa Tyson and Meredith Watson make it clear that Lt. Gov Fairfax should resign. My heart goes out to these brave women and their families.", "time": "2019-02-08T18:30:30-05:00", "link": "https://www.twitter.com/ewarren/statuses/1094015645895835655", "source": "Twitter Web Client"}, {"user_id": "357606935", "id": "1094032671003590657", "screen_name": "ewarren", "text": "The majority of Americans \u2013 Democrats, Republicans, and independents \u2013 support my #UltraMillionaireTax plan to start rebuilding our middle class. People are tired of a government that only works for the rich and powerful. https://thehill.com/hilltv/what-americas-thinking/428747-new-poll-americans-overwhelmingly-support-taxing-the-wealth-of", "time": "2019-02-08T19:38:09-05:00", "link": "https://www.twitter.com/ewarren/statuses/1094032671003590657", "source": "Twitter Web Client"}, {"user_id": "970207298", "id": "1093943381124894720", "screen_name": "SenWarren", "text": "Ready. https://twitter.com/PattyMurray/status/1093928537764085761 QT @PattyMurray Justice Kavanaugh has started attacking Roe v. Wade from the bench\u2014&amp; that means women &amp; men who believe women should have access to safe, legal abortion must stand up stronger than ever for women\u2019s constitutionally protected health care rights. I\u2019m ready &amp; I hope you are too.", "time": "2019-02-08T13:43:21-05:00", "link": "https://www.twitter.com/SenWarren/statuses/1093943381124894720", "source": "Twitter Web Client"}, {"user_id": "15764644", "id": "1093865495395254272", "screen_name": "SpeakerPelosi", "text": "RT @RepMikeLevin Honored to join so many strong leaders as a member of the Select Committee on the Climate Crisis. Together, we will answer the American people\u2019s call to #ActOnClimate with the energy &amp; urgency that was missing under Republican control. https://medium.com/@SpeakerPelosi/speaker-pelosi-names-members-of-the-select-committee-on-the-climate-crisis-7dc0c01f046d", "time": "2019-02-08T08:33:51-05:00", "link": "https://www.twitter.com/RepMikeLevin/statuses/1093863107636674561", "source": "Twitter Web App"}, {"user_id": "15745368", "id": "1093964418264821767", "screen_name": "marcorubio", "text": "Hunger &amp; desperation is growing inside #Venezuela &amp; people know the only thing standing in the way of $50 million of food &amp; medicine is #Maduro. \n\nMilitary leaders should make a choice, before a choice is made for them. The window for a negotiated exit is closing fast. https://twitter.com/reutersvzla/status/1093961797021904898 QT @ReutersVzla \u201cWe\u2019re still having conversations with members of the former Maduro regime, with military members, although those conversations are very, very limited.\u201d https://twitter.com/ReutersVzla/status/1093961647721459714", "time": "2019-02-08T15:06:56-05:00", "link": "https://www.twitter.com/marcorubio/statuses/1093964418264821767", "source": "Twitter for iPad"}, {"user_id": "357606935", "id": "1093896933805121537", "screen_name": "ewarren", "text": "William Barr has an appalling criminal justice record, supported efforts to gut the ACA, and expressed bias against the Mueller investigation. The Senate should absolutely vote No on his nomination. https://www.washingtonpost.com/world/national-security/senate-judiciary-committee-expected-to-advance-barrs-nomination-to-become-attorney-general/2019/02/06/005f1ca6-2983-11e9-b011-d8500644dc98_story.html", "time": "2019-02-08T10:38:47-05:00", "link": "https://www.twitter.com/ewarren/statuses/1093896933805121537", "source": "Twitter Web Client"}, {"user_id": "803694179079458816", "id": "1093980488316973061", "screen_name": "SenKamalaHarris", "text": "ICYMI \u2013 I wrote an op-ed this week on someone very dear to me who was like a second mother, Mrs. Shelton. I wouldn\u2019t be the person I am today without her. https://www.bustle.com/p/without-this-woman-i-wouldnt-be-the-senator-i-am-today-15910352", "time": "2019-02-08T16:10:48-05:00", "link": "https://www.twitter.com/SenKamalaHarris/statuses/1093980488316973061", "source": "Twitter Web Client"}, {"user_id": "29442313", "id": "1093940249754042368", "screen_name": "SenSanders", "text": "I am proud to be an original co-sponsor of the Green New Deal proposal. We must address the existential crisis of planetary climate change, while at the same time creating millions of good-paying jobs in our country. http://pbs.twimg.com/amplify_video_thumb/1093937749797806080/img/SGUEMZbKo1hHpO1R.jpg https://video.twimg.com/amplify_video/1093937749797806080/vid/320x320/F1_2NOMTz53-L-NJ.mp4?tag=9", "time": "2019-02-08T13:30:54-05:00", "link": "https://www.twitter.com/SenSanders/statuses/1093940249754042368", "source": "Twitter Media Studio"}, {"user_id": "229966028", "id": "1093939009825452033", "screen_name": "SenRubioPress", "text": "Detained Russian activist Anastasia Shevchenko faces up to 6 yrs in prison for belonging to an \u201cundesirable organization\u201d. Russian authorities cruelly restricted her access to her dying daughter. Putin's regime should release her immediately. #ExpressionNOToppression http://pbs.twimg.com/media/Dy5ztAlX4AEhCIs.jpg", "time": "2019-02-08T13:25:59-05:00", "link": "https://www.twitter.com/SenRubioPress/statuses/1093939009825452033", "source": "Twitter Web Client"}, {"user_id": "15745368", "id": "1093951846895497216", "screen_name": "marcorubio", "text": "Want proof of senseless &amp; irrational obstruction by some senate democrats?\n\nJudge Rodney Smith is a qualified &amp; mainstream #Florida judge with not a hint of scandal or controversy. \n\nYet yesterday 5 Dems on judiciary committee voted against his nomination to be a federal judge. http://pbs.twimg.com/media/Dy5_TxnWwAAxZjB.jpg", "time": "2019-02-08T14:16:59-05:00", "link": "https://www.twitter.com/marcorubio/statuses/1093951846895497216", "source": "Twitter for iPad"}, {"user_id": "1074480192", "id": "1093942535238623233", "screen_name": "SenTedCruz", "text": "GOP Seeks Its Soul on Foreign Policy; Sen. Ted Cruz May Have Found It https://www.redstate.com/slee/2019/02/06/gop-seeks-soul-foreign-policy-ted-cruz-may-found/", "time": "2019-02-08T13:39:59-05:00", "link": "https://www.twitter.com/SenTedCruz/statuses/1093942535238623233", "source": "Twitter Web Client"}, {"user_id": "2461810448", "id": "1093999196821106688", "screen_name": "TeamPelosi", "text": "RT @TeamPelosi Remember: whatever Trump says about House Democrats, he's projecting his own unruliness. \n\nWe will not surrender our constitutional responsibility for oversight. That would make us delinquent in our duties.", "time": "2019-02-08T17:25:08-05:00", "link": "https://www.twitter.com/TeamPelosi/statuses/1093547614153465856", "source": "Twitter Web Client"}, {"user_id": "15745368", "id": "1093920973731127296", "screen_name": "marcorubio", "text": "First visited canals in #MarathonFlorida right after #HurricaneIrma. Then went to D.C. to get the $ to clean them up.\n\nVisited a 2nd time when work began on clean up.\n\nToday came for the 3rd time. 142 of 172 canals have been cleared of debris. \n\n#Sayfie http://pbs.twimg.com/media/Dy5jTXMW0AAFApm.jpg http://pbs.twimg.com/media/Dy5jTW6X0AAMN7Y.jpg", "time": "2019-02-08T12:14:18-05:00", "link": "https://www.twitter.com/marcorubio/statuses/1093920973731127296", "source": "Twitter for iPad"}, {"user_id": "138203134", "id": "1093881089028997120", "screen_name": "AOC", "text": "Unlike these people, I actually care about my community. This happened across my old campaign office.\n\nWe\u2019ve been monitoring this heartbreaking situation and have been working with the community to heal.\n\nMeanwhile, ICE is detaining children, political activists &amp; 21 Savage. https://twitter.com/thedailybeast/status/1093878596685451264 QT @thedailybeast \"Fox &amp; Friends\" tried to blame @AOC for a fatal subway shooting that happened in her district: \"Ocasio-Cortez after, I imagine, seeing this horror, is upset that ICE even exists.\" https://www.thedailybeast.com/fox-and-friends-tries-to-blame-alexandria-ocasio-cortez-for-fatal-subway-shootin?via=twitter_page", "time": "2019-02-08T09:35:49-05:00", "link": "https://www.twitter.com/AOC/statuses/1093881089028997120", "source": "Twitter for iPhone"}, {"user_id": "15745368", "id": "1093926969681559553", "screen_name": "marcorubio", "text": "U.S. sanctions on oil will not hurt the people of #Venezuela because the people were not getting any of that money.\n\nCash from oil sales was being stolen by #Maduro &amp; given to regime insiders in order to buy their \u201cloyalty\u201d. https://nyti.ms/2UNO4C6?smid=nytcore-ios-share", "time": "2019-02-08T12:38:08-05:00", "link": "https://www.twitter.com/marcorubio/statuses/1093926969681559553", "source": "Twitter for iPad"}, {"user_id": "15808765", "id": "1093934338520043520", "screen_name": "CoryBooker", "text": "Today marks 51 years since one of the most violent moments in the civil rights movement in Orangeburg, SC where 3 students were killed and 28 people were injured protesting segregation. We honor the victims by continuing their fight for justice &amp; equality. https://www.postandcourier.com/news/orangeburg-massacre-survivors-fight-for-remembrance-of-bloodiest-civil-rights/article_66cd9b1e-0604-11e8-a307-036240bdda75.html", "time": "2019-02-08T13:07:25-05:00", "link": "https://www.twitter.com/CoryBooker/statuses/1093934338520043520", "source": "Twitter Web Client"}, {"user_id": "30354991", "id": "1093846446875516928", "screen_name": "KamalaHarris", "text": "Good morning! I\u2019m going to be on-air with Tom Joyner of the @TJMShow next \u2192 http://mobileui.clipinteractive.com/webplayer?stationUrl=TOMJOYNER", "time": "2019-02-08T07:18:10-05:00", "link": "https://www.twitter.com/KamalaHarris/statuses/1093846446875516928", "source": "Sprout Social"}, {"user_id": "229966028", "id": "1093905525883002886", "screen_name": "SenRubioPress", "text": "RT @IRIglobal On Monday, IRI Board Member @marcorubio will discuss the political developments in #Venezuela at a joint IRI and @Heritage event. RSVP here: https://www.heritage.org/global-politics/event/venezuela-tipping-point?utm_medium=social&utm_source=twitter&utm_campaign=thf-tw #RubioAtHeritage", "time": "2019-02-08T11:12:55-05:00", "link": "https://www.twitter.com/IRIglobal/statuses/1093900539052679169", "source": "Twitter Web Client"}, {"user_id": "15745368", "id": "1093909290350448640", "screen_name": "marcorubio", "text": "As his colleague I can tell you that at a time of so much bitterness &amp; anger we need more people like @ChrisCoons.  \n\nIf we had more people with his heart, the Senate &amp; America would be better for it. https://twitter.com/chriscoons/status/1093651921859162117 QT @ChrisCoons I don\u2019t have 1000 words for this photo (credit to @AP photographer @evanvucci) but I do have some.\n\nIt's no secret that I don't agree with President Trump very often, but I pray for the President regularly, as I did at today\u2019s National Prayer Breakfast. http://pbs.twimg.com/media/Dy1un_zWkAExVt_.jpg", "time": "2019-02-08T11:27:53-05:00", "link": "https://www.twitter.com/marcorubio/statuses/1093909290350448640", "source": "Twitter for iPad"}, {"user_id": "1078693601356509184", "id": "1093938970545786880", "screen_name": "SenatorRomney", "text": "RT @UTNationalGuard Governor Gary Herbert recognizes four families of fallen service members today in the Gold Room at the Utah State Capitol Capitol. (Photo: Maj. Brent Taylor family) @ Utah State Capitol https://www.instagram.com/p/BtoWU49HMnF/?utm_source=ig_twitter_share&igshid=1hyj1ytmet0zy", "time": "2019-02-08T13:25:49-05:00", "link": "https://www.twitter.com/UTNationalGuard/statuses/1093935934691655681", "source": "Twitter Web Client"}, {"user_id": "138203134", "id": "1093879024445808641", "screen_name": "AOC", "text": "@IlhanMN Love you sister. Thank you for your testimony, and for fighting for little girls with big dreams all over the world.\n\nYou are their shining hope, and together we will keep the door open and safe.", "time": "2019-02-08T09:27:37-05:00", "link": "https://www.twitter.com/AOC/statuses/1093879024445808641", "source": "Twitter for iPhone"}, {"user_id": "229966028", "id": "1093966491354050560", "screen_name": "SenRubioPress", "text": "Joined Senator @RonWyden in requesting @DHSgov to investigate foreign-made Virtual Private Network (VPN) apps, affiliated with countries such as #Russia and #China. \nhttps://www.rubio.senate.gov/public/index.cfm/press-releases?ID=34F0B041-4CFF-4716-9FC3-F7DD1D288970", "time": "2019-02-08T15:15:11-05:00", "link": "https://www.twitter.com/SenRubioPress/statuses/1093966491354050560", "source": "Twitter Web Client"}, {"user_id": "357606935", "id": "1093949276227555328", "screen_name": "ewarren", "text": "The big Wall Street banks shaved a cool $21 BILLION off their taxes last year, thanks to Donald Trump\u2019s #GOPTaxScam. It makes me wonder what else we could do with that money. Childcare? A #GreenNewDeal? Student loan forgiveness? https://www.bloomberg.com/news/articles/2019-02-06/banks-reaping-21-billion-tax-windfall-cut-staff-ease-off-loans", "time": "2019-02-08T14:06:46-05:00", "link": "https://www.twitter.com/ewarren/statuses/1093949276227555328", "source": "Twitter Web Client"}, {"user_id": "15745368", "id": "1093900211691417600", "screen_name": "marcorubio", "text": "We are at risk of losing our ecologically &amp; economically valuable Coral Reefs in the #FloridaKeys. \n\nI will be working on crafting a Coral Reef Restoration Plan. Today I visited the Natl Marine Sanctuary in #KeyLargo to discuss it.\n\n #Sayfie http://pbs.twimg.com/media/Dy5QcK9WsAAT_n1.jpg", "time": "2019-02-08T10:51:48-05:00", "link": "https://www.twitter.com/marcorubio/statuses/1093900211691417600", "source": "Twitter for iPad"}, {"user_id": "138203134", "id": "1093962540546166787", "screen_name": "AOC", "text": "@chrissyteigen yes! we can live-tweet me burning something in the kitchen", "time": "2019-02-08T14:59:29-05:00", "link": "https://www.twitter.com/AOC/statuses/1093962540546166787", "source": "Twitter for iPhone"}, {"user_id": "1078693601356509184", "id": "1093980697302306821", "screen_name": "SenatorRomney", "text": "Had the opportunity to sample Utah\u2019s Best Tasting Water for 2018 while meeting with the @UtahRuralWater Association to discuss water issues within our state. Utah\u2019s water is mighty fine! http://pbs.twimg.com/media/Dy6ZlFdW0AM7mtP.jpg http://pbs.twimg.com/media/Dy6ZlcnX4AE0MTk.jpg", "time": "2019-02-08T16:11:38-05:00", "link": "https://www.twitter.com/SenatorRomney/statuses/1093980697302306821", "source": "Twitter Web Client"}, {"user_id": "15808765", "id": "1093918574324916225", "screen_name": "CoryBooker", "text": "The first question I was asked in Iowa was about #GreenNewDeal. The hard truth is climate change has imperiled our planet\u2014it\u2019s going to take bold action now to save it including dramatic investment in green energy that will create the jobs of the future. We can do this. http://pbs.twimg.com/amplify_video_thumb/1093917557298511873/img/e5LexUGl7orMMnkw.jpg https://video.twimg.com/amplify_video/1093917557298511873/vid/320x180/T2onrd0KRl06h9Iz.mp4?tag=9", "time": "2019-02-08T12:04:46-05:00", "link": "https://www.twitter.com/CoryBooker/statuses/1093918574324916225", "source": "Twitter Media Studio"}, {"user_id": "138203134", "id": "1093922871666229248", "screen_name": "AOC", "text": "When your #GreenNewDeal legislation is so strong that the GOP has to resort to circulating false versions, but the real one nets 70 House cosponsors on Day 1 and all Dem presidential candidates sign on anyway https://twitter.com/crislopezg/status/1093921017205063680 QT @crislopezg look at these morons trying to gorilla channel @aoc's green new deal http://pbs.twimg.com/media/Dy5jRmcWsAA4Q5s.jpg http://pbs.twimg.com/media/Dy5jRmXXQAA50jb.jpg", "time": "2019-02-08T12:21:51-05:00", "link": "https://www.twitter.com/AOC/statuses/1093922871666229248", "source": "Twitter for iPhone"}, {"user_id": "15745368", "id": "1093960392378892290", "screen_name": "marcorubio", "text": "Despite terrible things some military leaders in #Venezuela have done,I have long advised that U.S. should honor the amnesty National Assembly offered those who cut ties with #Maduro. \n\nBut any military officer that helps starve their own people by blocking aid is disqualified. http://pbs.twimg.com/media/Dy6HJ2_X0AAa8rq.jpg http://pbs.twimg.com/media/Dy6HJ3BWwAcpoGT.jpg", "time": "2019-02-08T14:50:57-05:00", "link": "https://www.twitter.com/marcorubio/statuses/1093960392378892290", "source": "Twitter for iPad"}, {"user_id": "1078693601356509184", "id": "1093951079103021058", "screen_name": "SenatorRomney", "text": "RT @utahsenate Today, we had the privilege of honoring Utah\u2019s fallen soldiers on the Senate floor to give thanks for the service they and their families have given to this country. The entire Senate body stood and observed a moment of silence to commemorate the soldiers. #utpol #utleg #thankyou http://pbs.twimg.com/media/Dy577gPU0AASuZA.jpg", "time": "2019-02-08T14:13:56-05:00", "link": "https://www.twitter.com/utahsenate/statuses/1093948032280715264", "source": "Twitter Web Client"}, {"user_id": "138203134", "id": "1094065385828220930", "screen_name": "AOC", "text": "jay smooth gets it more than most people in DC do \u2b07\ufe0f https://twitter.com/jsmooth995/status/1093903173096493057 QT @jsmooth995 About @AOC's Green New Deal and \"wondering what the polls will say.\" #YellingAtBadTweets http://pbs.twimg.com/ext_tw_video_thumb/1093899220996800514/pu/img/O6DcSf-uok6BKboM.jpg https://video.twimg.com/ext_tw_video/1093899220996800514/pu/vid/320x180/sXKWRbyUc0ZdCwva.mp4?tag=6", "time": "2019-02-08T21:48:09-05:00", "link": "https://www.twitter.com/AOC/statuses/1094065385828220930", "source": "Twitter for iPhone"}, {"user_id": "30354991", "id": "1093841964502581248", "screen_name": "KamalaHarris", "text": "Good morning! I\u2019m going to be on-air with Tom Joyner of the @TJMShow next \u2192 http://blackamericaweb.com/where-to-listen/", "time": "2019-02-08T07:00:21-05:00", "link": "https://www.twitter.com/KamalaHarris/statuses/1093841964502581248", "source": "Sprout Social"}, {"user_id": "15764644", "id": "1093993709367115778", "screen_name": "SpeakerPelosi", "text": "This #BlackHistoryMonth, @RepBarbaraLee reminds us that the fight to deliver progress #ForThePeople is far from over. http://pbs.twimg.com/amplify_video_thumb/1093981577489629185/img/lakXkmzUd-pLGbd0.jpg https://video.twimg.com/amplify_video/1093981577489629185/vid/320x180/_L-Irfid12J2SiV2.mp4?tag=9", "time": "2019-02-08T17:03:20-05:00", "link": "https://www.twitter.com/SpeakerPelosi/statuses/1093993709367115778", "source": "Twitter Media Studio"}, {"user_id": "30354991", "id": "1094047917122506752", "screen_name": "KamalaHarris", "text": "The allegations by Dr. Vanessa Tyson and Meredith Watson are corroborated, painful stories of sexual assault and rape. It\u2019s clear Virginia Lieutenant Governor Justin Fairfax should resign his office.", "time": "2019-02-08T20:38:44-05:00", "link": "https://www.twitter.com/KamalaHarris/statuses/1094047917122506752", "source": "Twitter for Android"}, {"user_id": "229966028", "id": "1093938613124038657", "screen_name": "SenRubioPress", "text": "RT @marcorubio Lady Bradley is a beautiful 170lb loggerhead turtle. \n\nShe was entangled in a trap line off the upper #FloridaKeys last November. But she has made a full recovery thanks to @TurtleHospital.\n\nToday I was in #SombreroBeach  as she returned to her ocean home.\n\n#Sayfie http://pbs.twimg.com/media/Dy5xo3zW0AAumZd.jpg", "time": "2019-02-08T13:24:24-05:00", "link": "https://www.twitter.com/marcorubio/statuses/1093936739448745985", "source": "Twitter Web Client"}, {"user_id": "15808765", "id": "1093865692116467713", "screen_name": "CoryBooker", "text": "Grateful to kick off my first Iowa trip as a presidential candidate surrounded by 5 generations of family at my Aunt Alma's home. All that I am is because of the work, sacrifice and love of my ancestors. As I said last night, I'm going to run a campaign my family can be proud of. http://pbs.twimg.com/media/Dy4woyRWsAA31VB.jpg http://pbs.twimg.com/media/Dy4woySXgAAuDsW.jpg http://pbs.twimg.com/media/Dy4woyWW0AA3qZU.jpg", "time": "2019-02-08T08:34:38-05:00", "link": "https://www.twitter.com/CoryBooker/statuses/1093865692116467713", "source": "Twitter Web Client"}, {"user_id": "15808765", "id": "1094005695756886017", "screen_name": "CoryBooker", "text": "The multiple detailed allegations against the Lt. Gov. of Virginia are deeply troubling. They are serious, credible, and corroborated by others. It is no longer appropriate for him to serve. He should resign.", "time": "2019-02-08T17:50:58-05:00", "link": "https://www.twitter.com/CoryBooker/statuses/1094005695756886017", "source": "Twitter Web Client"}, {"user_id": "138203134", "id": "1093962178099662851", "screen_name": "AOC", "text": "RT @SSWorks \"I reject the idea that universal healthcare is impossible...We need to return to our FDR roots as a party.\" - @AOC \n\n#MedicareForAll http://pbs.twimg.com/ext_tw_video_thumb/1093944572919644161/pu/img/bB95Fn_ZJ9TFTnXY.jpg https://video.twimg.com/ext_tw_video/1093944572919644161/pu/vid/320x320/alKo21bf1MDQULxr.mp4?tag=6", "time": "2019-02-08T14:58:02-05:00", "link": "https://www.twitter.com/SSWorks/statuses/1093944757905178624", "source": "Twitter for iPhone"}, {"user_id": "15764644", "id": "1093972342143881216", "screen_name": "SpeakerPelosi", "text": "Chairman @JohnDingell had a hand in crafting many major legislative accomplishments over the past half-century \u2013 but few hold greater meaning than his tireless commitment to the health of the American people. His memory will stand as an inspiration to all Americans. http://pbs.twimg.com/media/Dy6R8JpXQAEqX6j.jpg https://video.twimg.com/amplify_video/1093970749692563456/vid/320x180/N-sLx7YdR27Al0g8.mp4?tag=9", "time": "2019-02-08T15:38:26-05:00", "link": "https://www.twitter.com/SpeakerPelosi/statuses/1093972342143881216", "source": "Twitter Media Studio"}, {"user_id": "229966028", "id": "1094003014292160512", "screen_name": "SenRubioPress", "text": "Last April, I toured canal debris in #Marathon, #Florida. I returned to D.C. to continue my fight for Florida in Congress, securing funds for #HurricaneIrma recovery. Today I returned to survey the continued recovery efforts. #sayfie http://pbs.twimg.com/media/Dy6t65qWsAYOwT1.jpg http://pbs.twimg.com/media/Dy6t66ZWoAMNCkW.jpg", "time": "2019-02-08T17:40:18-05:00", "link": "https://www.twitter.com/SenRubioPress/statuses/1094003014292160512", "source": "Twitter Web Client"}, {"user_id": "970207298", "id": "1094008404933308417", "screen_name": "SenWarren", "text": "A bank teller who takes a few 20s from the bank is looking at serious jail time. But the @WellsFargo CEO can cheat millions of Americans and walk away. That\u2019s a rigged system - and it needs to change. http://pbs.twimg.com/media/Dvs9CPlWsAAzH9i.jpg https://video.twimg.com/amplify_video/1079520566812594181/vid/320x180/D1h4Xy_578jvTDgq.mp4?tag=9", "time": "2019-02-08T18:01:44-05:00", "link": "https://www.twitter.com/SenWarren/statuses/1094008404933308417", "source": "Twitter Media Studio"}, {"user_id": "229966028", "id": "1093900383217467392", "screen_name": "SenRubioPress", "text": "RT @marcorubio We are at risk of losing our ecologically &amp; economically valuable Coral Reefs in the #FloridaKeys. \n\nI will be working on crafting a Coral Reef Restoration Plan. Today I visited the Natl Marine Sanctuary in #KeyLargo to discuss it.\n\n #Sayfie http://pbs.twimg.com/media/Dy5QcK9WsAAT_n1.jpg", "time": "2019-02-08T10:52:29-05:00", "link": "https://www.twitter.com/marcorubio/statuses/1093900211691417600", "source": "Twitter Web Client"}, {"user_id": "357606935", "id": "1093912389370695680", "screen_name": "ewarren", "text": "Tomorrow\u2019s a big day for our grassroots movement &amp; I hope you\u2019ll join us in Lawrence, MA tomorrow. I\u2019m announcing some big 2020 plans \u2013 &amp; I want you to be a part of it. RSVP: https://my.elizabethwarren.com/page/s/join-elizabeth-in-lawrence-?source=20190208tw", "time": "2019-02-08T11:40:12-05:00", "link": "https://www.twitter.com/ewarren/statuses/1093912389370695680", "source": "Twitter Web Client"}, {"user_id": "1074480192", "id": "1094046173244129280", "screen_name": "SenTedCruz", "text": "Great work by the courageous men and women who guard the Texas border. This poison flowing into our country must be stopped. #SecureTheBorder \u2014&gt; UPDATE: 1,000 pounds of methamphetamine seized at Pharr port of entry https://www.themonitor.com/2019/02/07/chief-alamo-police-net-largest-meth-seizure/ via @The Monitor", "time": "2019-02-08T20:31:48-05:00", "link": "https://www.twitter.com/SenTedCruz/statuses/1094046173244129280", "source": "Twitter for iPhone"}, {"user_id": "30354991", "id": "1093999917167718400", "screen_name": "KamalaHarris", "text": "Unaccompanied immigrant children need our help getting back into safe, nurturing homes. They don\u2019t belong in detention facilities. Yesterday, my colleagues &amp; I reintroduced the Families Not Facilities Act, which would prohibit ICE from using caretakers\u2019 info if they came forward.", "time": "2019-02-08T17:28:00-05:00", "link": "https://www.twitter.com/KamalaHarris/statuses/1093999917167718400", "source": "Sprout Social"}, {"user_id": "1074480192", "id": "1093873690683588613", "screen_name": "SenTedCruz", "text": "Troubling story on now-public report suggesting Congress was misled about Palestinian terror incitement and US funding. Cites my campaign against incitement in Palestinian educational system. --&gt; http://jewishinsider.com/15567/", "time": "2019-02-08T09:06:25-05:00", "link": "https://www.twitter.com/SenTedCruz/statuses/1093873690683588613", "source": "Twitter Web Client"}, {"user_id": "229966028", "id": "1093979258819694594", "screen_name": "SenRubioPress", "text": "RT @cnalive #BREAKING: In an exclusive interview with CNA, @marcorubio said that blocking aid to #Venezuela is a \"crime against humanity.\" https://www.catholicnewsagency.com/news/rubio-blocking-aid-to-venezuela-is-a-crime-against-humanity-21754", "time": "2019-02-08T16:05:55-05:00", "link": "https://www.twitter.com/cnalive/statuses/1093975264000966657", "source": "Twitter Web Client"}, {"user_id": "23022687", "id": "1093944392405049344", "screen_name": "tedcruz", "text": "RT @TheRealBuzz To my friends and colleagues who made the ultimate sacrifice in the name of space exploration...I salute you. \ud83c\uddfa\ud83c\uddf8 https://twitter.com/JimBridenstine/status/1093586413432508417 QT @JimBridenstine Today, we honor the Apollo 1, Challenger and Columbia crews, as well as other members of the @NASA family who lost their lives supporting NASA\u2019s mission of exploration. We are deeply grateful to all of them and will always strive to honor their legacy. #NASARemembers \ud83c\uddfa\ud83c\uddf8 http://pbs.twimg.com/media/Dy0zB3JWoAAnkVW.jpg http://pbs.twimg.com/media/Dy0zB3HWwAAuco4.jpg", "time": "2019-02-08T13:47:22-05:00", "link": "https://www.twitter.com/TheRealBuzz/statuses/1093708570896596997", "source": "Twitter for iPhone"}, {"user_id": "15808765", "id": "1094088723355107328", "screen_name": "CoryBooker", "text": "Incredible day in Iowa (and still going!) I told my staff to buckle up\u2014I\u2019m going to be a candidate that goes to everybody I possibly can, to every community and every neighborhood. Honored to start this journey in Mason City. http://pbs.twimg.com/media/Dy77tNRW0AIJsP0.jpg http://pbs.twimg.com/media/Dy77tNSWwAAcBgx.jpg http://pbs.twimg.com/media/Dy77tO3W0AAyg5_.jpg http://pbs.twimg.com/media/Dy77tOzXgAAjAQG.jpg", "time": "2019-02-08T23:20:53-05:00", "link": "https://www.twitter.com/CoryBooker/statuses/1094088723355107328", "source": "Twitter Web Client"}, {"user_id": "2461810448", "id": "1094086956072484864", "screen_name": "TeamPelosi", "text": "RT @JackieSpeier Thank you, @TeamPelosi! The adults are back in charge are we're going to stop @realDonaldTrump from shutting down our government and putting families at risk again. https://thehill.com/homenews/house/428891-pelosi-there-will-not-be-another-shutdown", "time": "2019-02-08T23:13:52-05:00", "link": "https://www.twitter.com/JackieSpeier/statuses/1094086489942700032", "source": "Twitter for iPhone"}, {"user_id": "15745368", "id": "1093936739448745985", "screen_name": "marcorubio", "text": "Lady Bradley is a beautiful 170lb loggerhead turtle. \n\nShe was entangled in a trap line off the upper #FloridaKeys last November. But she has made a full recovery thanks to @TurtleHospital.\n\nToday I was in #SombreroBeach  as she returned to her ocean home.\n\n#Sayfie http://pbs.twimg.com/media/Dy5xo3zW0AAumZd.jpg", "time": "2019-02-08T13:16:57-05:00", "link": "https://www.twitter.com/marcorubio/statuses/1093936739448745985", "source": "Twitter for iPad"}, {"user_id": "15764644", "id": "1094008088804376576", "screen_name": "SpeakerPelosi", "text": "Frank Robinson\u2019s impact was felt long after he retired his glove to make history &amp; become the first African American manager for both my hometown teams, @SFGiants &amp; @Orioles. His leadership on and off the field will be remembered for years to come.", "time": "2019-02-08T18:00:28-05:00", "link": "https://www.twitter.com/SpeakerPelosi/statuses/1094008088804376576", "source": "Sprout Social"}, {"user_id": "229966028", "id": "1093938650218483712", "screen_name": "SenRubioPress", "text": "Happy to see @FEMA award $61 million dollars in additional grants to #PuertoRico for expenses related to hurricanes Irma and Maria. The federal government must continue to work in support of our fellow citizens as they continue to recover.\nhttps://caribbeanbusiness.com/fema-approves-61-million-in-additional-grants-to-puerto-rico/", "time": "2019-02-08T13:24:33-05:00", "link": "https://www.twitter.com/SenRubioPress/statuses/1093938650218483712", "source": "Twitter Web Client"}, {"user_id": "357606935", "id": "1093978396458131457", "screen_name": "ewarren", "text": "I'm fired up about the movement we're building \u2013 are you in? Tune in live on Saturday at 11 AM when I announce my plans. https://my.elizabethwarren.com/page/s/watch-elizabeth-s-announcement-in-lawrence- http://pbs.twimg.com/media/Dy6XVR0WsAIHjWB.jpg https://video.twimg.com/amplify_video/1093976004584984576/vid/320x180/zTKsxLB9UnsBrp7L.mp4?tag=9", "time": "2019-02-08T16:02:29-05:00", "link": "https://www.twitter.com/ewarren/statuses/1093978396458131457", "source": "Twitter Media Studio"}, {"user_id": "29442313", "id": "1094050401576542208", "screen_name": "SenSanders", "text": "I agree with the joint statement from the Virginia House and Senate Democrats. Very serious and credible allegations have been made by two women against Lieutenant Governor Fairfax. He needs to resign.", "time": "2019-02-08T20:48:36-05:00", "link": "https://www.twitter.com/SenSanders/statuses/1094050401576542208", "source": "Twitter Web Client"}, {"user_id": "357606935", "id": "1093875602392797184", "screen_name": "ewarren", "text": "At Stonewall and through decades of activism, Marsha P. Johnson helped light the spark for LGBTQ+ rights and lead the charge for a more equal America. We won't stop fighting until everyone is free to be who they are &amp; live without fear. #BlackHistoryMonth https://www.nytimes.com/interactive/2018/obituaries/overlooked-marsha-p-johnson.html", "time": "2019-02-08T09:14:01-05:00", "link": "https://www.twitter.com/ewarren/statuses/1093875602392797184", "source": "Twitter Web Client"}, {"user_id": "30354991", "id": "1093926402427179009", "screen_name": "KamalaHarris", "text": "Today we remember Henry Smith, Samuel Hammond, and Delano Middleton who died on the campus of South Carolina State University in the fight to desegregate the South. \nhttps://www.postandcourier.com/news/orangeburg-massacre-survivors-fight-for-remembrance-of-bloodiest-civil-rights/article_66cd9b1e-0604-11e8-a307-036240bdda75.html", "time": "2019-02-08T12:35:53-05:00", "link": "https://www.twitter.com/KamalaHarris/statuses/1093926402427179009", "source": "Twitter Web Client"}, {"user_id": "1074480192", "id": "1093931988438921217", "screen_name": "SenTedCruz", "text": "RT @SenTedCruz HAMMER: Ted Cruz\u2019s \u2018Non-Interventionist Hawk\u2019 Foreign Policy Is Exactly Right https://www.dailywire.com/news/43151/hammer-ted-cruzs-non-interventionist-hawk-foreign-josh-hammer", "time": "2019-02-08T12:58:04-05:00", "link": "https://www.twitter.com/SenTedCruz/statuses/1093275552876777475", "source": "Twitter for iPhone"}, {"user_id": "23022687", "id": "1093944430233497600", "screen_name": "tedcruz", "text": "RT @JimBridenstine Today, we honor the Apollo 1, Challenger and Columbia crews, as well as other members of the @NASA family who lost their lives supporting NASA\u2019s mission of exploration. We are deeply grateful to all of them and will always strive to honor their legacy. #NASARemembers \ud83c\uddfa\ud83c\uddf8 http://pbs.twimg.com/media/Dy0zB3JWoAAnkVW.jpg http://pbs.twimg.com/media/Dy0zB3HWwAAuco4.jpg", "time": "2019-02-08T13:47:31-05:00", "link": "https://www.twitter.com/JimBridenstine/statuses/1093586413432508417", "source": "Twitter for iPhone"}, {"user_id": "216881337", "id": "1093894580301369344", "screen_name": "RandPaul", "text": "To call it a precipitous withdrawal after 17 years is ludicrous. We've been there 17 years. https://thehill.com/homenews/senate/427853-rand-paul-ludicrous-to-call-a-withdrawal-from-afghanistan-and-syria", "time": "2019-02-08T10:29:26-05:00", "link": "https://www.twitter.com/RandPaul/statuses/1093894580301369344", "source": "Buffer"}, {"user_id": "216881337", "id": "1093928652872527872", "screen_name": "RandPaul", "text": "While some would have us believe we can only protect the environment by giving the federal government more control over Americans\u2019 lives, my bill shows we can act while still respecting Americans\u2019 private property rights. https://www.paul.senate.gov/news/dr-rand-paul-reintroduces-defense-environment-and-property-act", "time": "2019-02-08T12:44:49-05:00", "link": "https://www.twitter.com/RandPaul/statuses/1093928652872527872", "source": "Buffer"}]